Workbook

Sheet 说明
A1: 页签名称 | B1: 数量 | C1: 说明
A2: JV and CTP清单 | B2: 850 | C2: TA的一级JV and CTP组织
A3: 公司清单 | B3: 2300 | C3: TA的全量组织
A4: 各板块数据 | B4: 1341 | C4: 各板块提交的组织清单

Sheet JV and CTP清单
A1: Entity List | H1: TMS映射 | L1: 关系-分部架构 | N1: 关系-地区架构 | P1: 关系-数据源架构
A2: 人为顺序编码 | E2: 自定义属性 | F2: 自定义属性 | G2: 自定义属性
A3: Code | B3: English Description | C3: 中文 description | D3: Currency | E3: Com Sec Code 1083 | F3: Com Sec Code 0003 | G3: Frango Code | H3: JV映射数量 | I3: JV映射关系 | J3: CTP映射数量 | K3: CTP映射关系 | L3: Node | M3: Node - Description | N3: Node | O3: Node - Description | P3: Node | Q3: Node - Description
A4: 00001 | B4: The Hong Kong and China Gas Company Limited | C4: 香港中华煤气有限公司 | D4: HKD | G4: HKCG | H4: =COUNTIF(JV映射!$C:$C,$A4) -> 0 | I4: {=_xlfn.IFNA(INDEX(JV映射!$A:$A,MATCH($A4,JV映射!$C:$C,0)),"")} | J4: =COUNTIF(CTP映射!$C:$C,$A4) -> 1 | K4: {=_xlfn.IFNA(INDEX(CTP映射!A:A,MATCH($A4,CTP映射!C:C,0)),"")} -> JYGLF0668 | L4: =VLOOKUP($A4,JV分部架构!$A:$F,5,0) -> ORG|HK_CORE | M4: =VLOOKUP($A4,JV分部架构!$A:$F,6,0) -> Hong Kong Business | N4: =VLOOKUP($A4,JV地区架构!$A:$F,5,0) -> LOC|HK | O4: =VLOOKUP($A4,JV地区架构!$A:$F,6,0) -> Hong Kong | P4: =VLOOKUP($A4,JV数据源架构!$A:$F,5,0) -> SRC|HK_SAP | Q4: =VLOOKUP($A4,JV数据源架构!$A:$F,6,0) -> SAP直接上报TA
A5: 00002 | B5: Skyward Investments Limited | C5: Skyward Investments Limited | D5: HKD | G5: SKYW | H5: =COUNTIF(JV映射!$C:$C,$A5) -> 0 | I5: {=_xlfn.IFNA(INDEX(JV映射!$A:$A,MATCH($A5,JV映射!$C:$C,0)),"")} | J5: =COUNTIF(CTP映射!$C:$C,$A5) -> 0 | K5: {=_xlfn.IFNA(INDEX(CTP映射!A:A,MATCH($A5,CTP映射!C:C,0)),"")} | L5: =VLOOKUP($A5,JV分部架构!$A:$F,5,0) -> ORG|HK_BUSINESS | M5: =VLOOKUP($A5,JV分部架构!$A:$F,6,0) -> HK Business | N5: =VLOOKUP($A5,JV地区架构!$A:$F,5,0) -> LOC|HK | O5: =VLOOKUP($A5,JV地区架构!$A:$F,6,0) -> Hong Kong | P5: =VLOOKUP($A5,JV数据源架构!$A:$F,5,0) -> SRC|HK_SAP | Q5: =VLOOKUP($A5,JV数据源架构!$A:$F,6,0) -> SAP直接上报TA
A6: 00003 | B6: Brilliant World International Limited | C6: Brilliant World International Limited | D6: HKD | G6: BRIL | H6: =COUNTIF(JV映射!$C:$C,$A6) -> 0 | I6: {=_xlfn.IFNA(INDEX(JV映射!$A:$A,MATCH($A6,JV映射!$C:$C,0)),"")} | J6: =COUNTIF(CTP映射!$C:$C,$A6) -> 0 | K6: {=_xlfn.IFNA(INDEX(CTP映射!A:A,MATCH($A6,CTP映射!C:C,0)),"")} | L6: =VLOOKUP($A6,JV分部架构!$A:$F,5,0) -> ORG|HK_BUSINESS | M6: =VLOOKUP($A6,JV分部架构!$A:$F,6,0) -> HK Business | N6: =VLOOKUP($A6,JV地区架构!$A:$F,5,0) -> LOC|BVI | O6: =VLOOKUP($A6,JV地区架构!$A:$F,6,0) -> BVI | P6: =VLOOKUP($A6,JV数据源架构!$A:$F,5,0) -> SRC|HK_SAP | Q6: =VLOOKUP($A6,JV数据源架构!$A:$F,6,0) -> SAP直接上报TA
A7: 00004 | B7: Edonlite Holdings Limited | C7: Edonlite Holdings Limited | D7: HKD | G7: EDON | H7: =COUNTIF(JV映射!$C:$C,$A7) -> 0 | I7: {=_xlfn.IFNA(INDEX(JV映射!$A:$A,MATCH($A7,JV映射!$C:$C,0)),"")} | J7: =COUNTIF(CTP映射!$C:$C,$A7) -> 0 | K7: {=_xlfn.IFNA(INDEX(CTP映射!A:A,MATCH($A7,CTP映射!C:C,0)),"")} | L7: =VLOOKUP($A7,JV分部架构!$A:$F,5,0) -> ORG|HK_BUSINESS | M7: =VLOOKUP($A7,JV分部架构!$A:$F,6,0) -> HK Business | N7: =VLOOKUP($A7,JV地区架构!$A:$F,5,0) -> LOC|BVI | O7: =VLOOKUP($A7,JV地区架构!$A:$F,6,0) -> BVI | P7: =VLOOKUP($A7,JV数据源架构!$A:$F,5,0) -> SRC|HK_SAP | Q7: =VLOOKUP($A7,JV数据源架构!$A:$F,6,0) -> SAP直接上报TA
A8: 00005 | B8: Primebay Investments Limited | C8: Primebay Investments Limited | D8: HKD | G8: PRIM | H8: =COUNTIF(JV映射!$C:$C,$A8) -> 0 | I8: {=_xlfn.IFNA(INDEX(JV映射!$A:$A,MATCH($A8,JV映射!$C:$C,0)),"")} | J8: =COUNTIF(CTP映射!$C:$C,$A8) -> 0 | K8: {=_xlfn.IFNA(INDEX(CTP映射!A:A,MATCH($A8,CTP映射!C:C,0)),"")} | L8: =VLOOKUP($A8,JV分部架构!$A:$F,5,0) -> ORG|HK_BUSINESS | M8: =VLOOKUP($A8,JV分部架构!$A:$F,6,0) -> HK Business | N8: =VLOOKUP($A8,JV地区架构!$A:$F,5,0) -> LOC|BVI | O8: =VLOOKUP($A8,JV地区架构!$A:$F,6,0) -> BVI | P8: =VLOOKUP($A8,JV数据源架构!$A:$F,5,0) -> SRC|HK_SAP | Q8: =VLOOKUP($A8,JV数据源架构!$A:$F,6,0) -> SAP直接上报TA
A9: 00006 | B9: China Guide Resources Limited | C9: 中诚资源有限公司 | D9: HKD | G9: GUID | H9: =COUNTIF(JV映射!$C:$C,$A9) -> 0 | I9: {=_xlfn.IFNA(INDEX(JV映射!$A:$A,MATCH($A9,JV映射!$C:$C,0)),"")} | J9: =COUNTIF(CTP映射!$C:$C,$A9) -> 1 | K9: {=_xlfn.IFNA(INDEX(CTP映射!A:A,MATCH($A9,CTP映射!C:C,0)),"")} -> JYGLF0716 | L9: =VLOOKUP($A9,JV分部架构!$A:$F,5,0) -> ORG|HK_BUSINESS | M9: =VLOOKUP($A9,JV分部架构!$A:$F,6,0) -> HK Business | N9: =VLOOKUP($A9,JV地区架构!$A:$F,5,0) -> LOC|HK | O9: =VLOOKUP($A9,JV地区架构!$A:$F,6,0) -> Hong Kong | P9: =VLOOKUP($A9,JV数据源架构!$A:$F,5,0) -> SRC|HK_SAP | Q9: =VLOOKUP($A9,JV数据源架构!$A:$F,6,0) -> SAP直接上报TA
A10: 00007 | B10: Smoothing Investment Limited | C10: 伟诚倡投资有限公司 | D10: HKD | G10: SMOO | H10: =COUNTIF(JV映射!$C:$C,$A10) -> 0 | I10: {=_xlfn.IFNA(INDEX(JV映射!$A:$A,MATCH($A10,JV映射!$C:$C,0)),"")} | J10: =COUNTIF(CTP映射!$C:$C,$A10) -> 0 | K10: {=_xlfn.IFNA(INDEX(CTP映射!A:A,MATCH($A10,CTP映射!C:C,0)),"")} | L10: =VLOOKUP($A10,JV分部架构!$A:$F,5,0) -> ORG|HK_BUSINESS | M10: =VLOOKUP($A10,JV分部架构!$A:$F,6,0) -> HK Business | N10: =VLOOKUP($A10,JV地区架构!$A:$F,5,0) -> LOC|HK | O10: =VLOOKUP($A10,JV地区架构!$A:$F,6,0) -> Hong Kong | P10: =VLOOKUP($A10,JV数据源架构!$A:$F,5,0) -> SRC|HK_SAP | Q10: =VLOOKUP($A10,JV数据源架构!$A:$F,6,0) -> SAP直接上报TA
A11: 00008 | B11: Quality Testing Services Limited | C11: 质量测检服务有限公司 | D11: HKD | G11: QUALR | H11: =COUNTIF(JV映射!$C:$C,$A11) -> 0 | I11: {=_xlfn.IFNA(INDEX(JV映射!$A:$A,MATCH($A11,JV映射!$C:$C,0)),"")} | J11: =COUNTIF(CTP映射!$C:$C,$A11) -> 1 | K11: {=_xlfn.IFNA(INDEX(CTP映射!A:A,MATCH($A11,CTP映射!C:C,0)),"")} -> JYGLF0699 | L11: =VLOOKUP($A11,JV分部架构!$A:$F,5,0) -> ORG|HK_BUSINESS | M11: =VLOOKUP($A11,JV分部架构!$A:$F,6,0) -> HK Business | N11: =VLOOKUP($A11,JV地区架构!$A:$F,5,0) -> LOC|HK | O11: =VLOOKUP($A11,JV地区架构!$A:$F,6,0) -> Hong Kong | P11: =VLOOKUP($A11,JV数据源架构!$A:$F,5,0) -> SRC|HK_SAP | Q11: =VLOOKUP($A11,JV数据源架构!$A:$F,6,0) -> SAP直接上报TA
A12: 00009 | B12: P-Tech Engineering Company Limited | C12: 卓诚工程有限公司 | D12: HKD | G12: TING | H12: =COUNTIF(JV映射!$C:$C,$A12) -> 0 | I12: {=_xlfn.IFNA(INDEX(JV映射!$A:$A,MATCH($A12,JV映射!$C:$C,0)),"")} | J12: =COUNTIF(CTP映射!$C:$C,$A12) -> 1 | K12: {=_xlfn.IFNA(INDEX(CTP映射!A:A,MATCH($A12,CTP映射!C:C,0)),"")} -> JYGLF0402 | L12: =VLOOKUP($A12,JV分部架构!$A:$F,5,0) -> ORG|P_TECH | M12: =VLOOKUP($A12,JV分部架构!$A:$F,6,0) -> P-Tech | N12: =VLOOKUP($A12,JV地区架构!$A:$F,5,0) -> LOC|HK | O12: =VLOOKUP($A12,JV地区架构!$A:$F,6,0) -> Hong Kong | P12: =VLOOKUP($A12,JV数据源架构!$A:$F,5,0) -> SRC|HK_SAP | Q12: =VLOOKUP($A12,JV数据源架构!$A:$F,6,0) -> SAP直接上报TA
A13: 00010 | B13: China Gas Company Limited | C13: 中华煤气有限公司 | D13: HKD | G13: CGAS | H13: =COUNTIF(JV映射!$C:$C,$A13) -> 0 | I13: {=_xlfn.IFNA(INDEX(JV映射!$A:$A,MATCH($A13,JV映射!$C:$C,0)),"")} | J13: =COUNTIF(CTP映射!$C:$C,$A13) -> 0 | K13: {=_xlfn.IFNA(INDEX(CTP映射!A:A,MATCH($A13,CTP映射!C:C,0)),"")} | L13: =VLOOKUP($A13,JV分部架构!$A:$F,5,0) -> ORG|HK_BUSINESS | M13: =VLOOKUP($A13,JV分部架构!$A:$F,6,0) -> HK Business | N13: =VLOOKUP($A13,JV地区架构!$A:$F,5,0) -> LOC|HK | O13: =VLOOKUP($A13,JV地区架构!$A:$F,6,0) -> Hong Kong | P13: =VLOOKUP($A13,JV数据源架构!$A:$F,5,0) -> SRC|HK_SAP | Q13: =VLOOKUP($A13,JV数据源架构!$A:$F,6,0) -> SAP直接上报TA
A14: 00011 | B14: Hong Kong Gas Company Limited | C14: 香港煤气有限公司 | D14: HKD | G14: HGAS | H14: =COUNTIF(JV映射!$C:$C,$A14) -> 0 | I14: {=_xlfn.IFNA(INDEX(JV映射!$A:$A,MATCH($A14,JV映射!$C:$C,0)),"")} | J14: =COUNTIF(CTP映射!$C:$C,$A14) -> 0 | K14: {=_xlfn.IFNA(INDEX(CTP映射!A:A,MATCH($A14,CTP映射!C:C,0)),"")} | L14: =VLOOKUP($A14,JV分部架构!$A:$F,5,0) -> ORG|HK_BUSINESS | M14: =VLOOKUP($A14,JV分部架构!$A:$F,6,0) -> HK Business | N14: =VLOOKUP($A14,JV地区架构!$A:$F,5,0) -> LOC|HK | O14: =VLOOKUP($A14,JV地区架构!$A:$F,6,0) -> Hong Kong | P14: =VLOOKUP($A14,JV数据源架构!$A:$F,5,0) -> SRC|HK_SAP | Q14: =VLOOKUP($A14,JV数据源架构!$A:$F,6,0) -> SAP直接上报TA
A15: 00012 | B15: Alpha Idea International Limited | C15: 星满国际有限公司 | D15: HKD | G15: AIIL | H15: =COUNTIF(JV映射!$C:$C,$A15) -> 0 | I15: {=_xlfn.IFNA(INDEX(JV映射!$A:$A,MATCH($A15,JV映射!$C:$C,0)),"")} | J15: =COUNTIF(CTP映射!$C:$C,$A15) -> 0 | K15: {=_xlfn.IFNA(INDEX(CTP映射!A:A,MATCH($A15,CTP映射!C:C,0)),"")} | L15: =VLOOKUP($A15,JV分部架构!$A:$F,5,0) -> ORG|EB_HK | M15: =VLOOKUP($A15,JV分部架构!$A:$F,6,0) -> Extended Business - Hong Kong | N15: =VLOOKUP($A15,JV地区架构!$A:$F,5,0) -> LOC|HK | O15: =VLOOKUP($A15,JV地区架构!$A:$F,6,0) -> Hong Kong | P15: =VLOOKUP($A15,JV数据源架构!$A:$F,5,0) -> SRC|HK_SAP | Q15: =VLOOKUP($A15,JV数据源架构!$A:$F,6,0) -> SAP直接上报TA
... A613: 00863 | B613: 威海港能投清洁能源有限公司 | C613: 威海港能投清洁能源有限公司 | D613: CNY | G613: SDWHPCE | H613: =COUNTIF(JV映射!$C:$C,$A613) -> 1 | I613: {=_xlfn.IFNA(INDEX(JV映射!$A:$A,MATCH($A613,JV映射!$C:$C,0)),"")} -> 384 | J613: =COUNTIF(CTP映射!$C:$C,$A613) -> 1 | K613: {=_xlfn.IFNA(INDEX(CTP映射!A:A,MATCH($A613,CTP映射!C:C,0)),"")} -> 384 | L613: =VLOOKUP($A613,JV分部架构!$A:$F,5,0) -> ORG|MU_RENEWABLE_ENERGY_TSEL | M613: =VLOOKUP($A613,JV分部架构!$A:$F,6,0) -> Renewable Energy (TSEL) | N613: =VLOOKUP($A613,JV地区架构!$A:$F,5,0) -> LOC|MLC_37 | O613: =VLOOKUP($A613,JV地区架构!$A:$F,6,0) -> Shandong | P613: =VLOOKUP($A613,JV数据源架构!$A:$F,5,0) -> SRC|DW_TMS | Q613: =VLOOKUP($A613,JV数据源架构!$A:$F,6,0) -> 通过DW上报TA（TMS）
A614: 00864 | B614: 滁州港华综合能源有限公司（合并） | C614: 滁州港华综合能源有限公司（合并） | D614: CNY | H614: =COUNTIF(JV映射!$C:$C,$A614) -> 1 | I614: {=_xlfn.IFNA(INDEX(JV映射!$A:$A,MATCH($A614,JV映射!$C:$C,0)),"")} -> AHCZNE | J614: =COUNTIF(CTP映射!$C:$C,$A614) -> 1 | K614: {=_xlfn.IFNA(INDEX(CTP映射!A:A,MATCH($A614,CTP映射!C:C,0)),"")} -> 381 | L614: =VLOOKUP($A614,JV分部架构!$A:$F,5,0) -> ORG|MU_RENEWABLE_ENERGY_TSEL | M614: =VLOOKUP($A614,JV分部架构!$A:$F,6,0) -> Renewable Energy (TSEL) | N614: =VLOOKUP($A614,JV地区架构!$A:$F,5,0) -> LOC|MLC_34 | O614: =VLOOKUP($A614,JV地区架构!$A:$F,6,0) -> Anhui | P614: =VLOOKUP($A614,JV数据源架构!$A:$F,5,0) -> SRC|DW_TMS | Q614: =VLOOKUP($A614,JV数据源架构!$A:$F,6,0) -> 通过DW上报TA（TMS）
A615: 00865 | B615: 海口港华智慧能源有限公司 | C615: 海口港华智慧能源有限公司 | D615: CNY | G615: HNHKGCE | H615: =COUNTIF(JV映射!$C:$C,$A615) -> 1 | I615: {=_xlfn.IFNA(INDEX(JV映射!$A:$A,MATCH($A615,JV映射!$C:$C,0)),"")} -> 393 | J615: =COUNTIF(CTP映射!$C:$C,$A615) -> 1 | K615: {=_xlfn.IFNA(INDEX(CTP映射!A:A,MATCH($A615,CTP映射!C:C,0)),"")} -> 393 | L615: =VLOOKUP($A615,JV分部架构!$A:$F,5,0) -> ORG|MU_RENEWABLE_ENERGY_TSEL | M615: =VLOOKUP($A615,JV分部架构!$A:$F,6,0) -> Renewable Energy (TSEL) | N615: =VLOOKUP($A615,JV地区架构!$A:$F,5,0) -> LOC|MLC_46 | O615: =VLOOKUP($A615,JV地区架构!$A:$F,6,0) -> Hainan | P615: =VLOOKUP($A615,JV数据源架构!$A:$F,5,0) -> SRC|DW_TMS | Q615: =VLOOKUP($A615,JV数据源架构!$A:$F,6,0) -> 通过DW上报TA（TMS）
A616: 00867 | B616: 柳州港能投智慧能源有限公司 | C616: 柳州港能投智慧能源有限公司 | D616: CNY | G616: GXLZPE | H616: =COUNTIF(JV映射!$C:$C,$A616) -> 1 | I616: {=_xlfn.IFNA(INDEX(JV映射!$A:$A,MATCH($A616,JV映射!$C:$C,0)),"")} -> 400 | J616: =COUNTIF(CTP映射!$C:$C,$A616) -> 2 | K616: {=_xlfn.IFNA(INDEX(CTP映射!A:A,MATCH($A616,CTP映射!C:C,0)),"")} -> 400 | L616: =VLOOKUP($A616,JV分部架构!$A:$F,5,0) -> ORG|MU_RENEWABLE_ENERGY_TSEL | M616: =VLOOKUP($A616,JV分部架构!$A:$F,6,0) -> Renewable Energy (TSEL) | N616: =VLOOKUP($A616,JV地区架构!$A:$F,5,0) -> LOC|MLC_45 | O616: =VLOOKUP($A616,JV地区架构!$A:$F,6,0) -> Guangxi | P616: =VLOOKUP($A616,JV数据源架构!$A:$F,5,0) -> SRC|DW_TMS | Q616: =VLOOKUP($A616,JV数据源架构!$A:$F,6,0) -> 通过DW上报TA（TMS）
A617: 00868 | B617: Anqiu TowngasChina PV PowerGenerationCo., Ltd. | C617: 安丘航洲新能源科技有限公司 | D617: CNY | G617: PGAQJV | H617: =COUNTIF(JV映射!$C:$C,$A617) -> 1 | I617: {=_xlfn.IFNA(INDEX(JV映射!$A:$A,MATCH($A617,JV映射!$C:$C,0)),"")} -> 216 | J617: =COUNTIF(CTP映射!$C:$C,$A617) -> 1 | K617: {=_xlfn.IFNA(INDEX(CTP映射!A:A,MATCH($A617,CTP映射!C:C,0)),"")} -> 216 | L617: =VLOOKUP($A617,JV分部架构!$A:$F,5,0) -> ORG|MU_RENEWABLE_ENERGY_TSEL | M617: =VLOOKUP($A617,JV分部架构!$A:$F,6,0) -> Renewable Energy (TSEL) | N617: =VLOOKUP($A617,JV地区架构!$A:$F,5,0) -> LOC|MLC_37 | O617: =VLOOKUP($A617,JV地区架构!$A:$F,6,0) -> Shandong | P617: =VLOOKUP($A617,JV数据源架构!$A:$F,5,0) -> SRC|DW_TMS | Q617: =VLOOKUP($A617,JV数据源架构!$A:$F,6,0) -> 通过DW上报TA（TMS）
A618: 00869 | B618: 青岛嘉嘉通新能源科技有限公司 | C618: 青岛嘉嘉通新能源科技有限公司 | D618: CNY | G618: PGQDJV | H618: =COUNTIF(JV映射!$C:$C,$A618) -> 1 | I618: {=_xlfn.IFNA(INDEX(JV映射!$A:$A,MATCH($A618,JV映射!$C:$C,0)),"")} -> 221 | J618: =COUNTIF(CTP映射!$C:$C,$A618) -> 1 | K618: {=_xlfn.IFNA(INDEX(CTP映射!A:A,MATCH($A618,CTP映射!C:C,0)),"")} -> 221 | L618: =VLOOKUP($A618,JV分部架构!$A:$F,5,0) -> ORG|MU_RENEWABLE_ENERGY_TSEL | M618: =VLOOKUP($A618,JV分部架构!$A:$F,6,0) -> Renewable Energy (TSEL) | N618: =VLOOKUP($A618,JV地区架构!$A:$F,5,0) -> LOC|MLC_37 | O618: =VLOOKUP($A618,JV地区架构!$A:$F,6,0) -> Shandong | P618: =VLOOKUP($A618,JV数据源架构!$A:$F,5,0) -> SRC|DW_TMS | Q618: =VLOOKUP($A618,JV数据源架构!$A:$F,6,0) -> 通过DW上报TA（TMS）
A619: 00870 | B619: 滨州鑫润丰新能源有限公司 | C619: 滨州鑫润丰新能源有限公司 | D619: CNY | G619: PGBZJV | H619: =COUNTIF(JV映射!$C:$C,$A619) -> 1 | I619: {=_xlfn.IFNA(INDEX(JV映射!$A:$A,MATCH($A619,JV映射!$C:$C,0)),"")} -> 253 | J619: =COUNTIF(CTP映射!$C:$C,$A619) -> 1 | K619: {=_xlfn.IFNA(INDEX(CTP映射!A:A,MATCH($A619,CTP映射!C:C,0)),"")} -> 253 | L619: =VLOOKUP($A619,JV分部架构!$A:$F,5,0) -> ORG|MU_RENEWABLE_ENERGY_TSEL | M619: =VLOOKUP($A619,JV分部架构!$A:$F,6,0) -> Renewable Energy (TSEL) | N619: =VLOOKUP($A619,JV地区架构!$A:$F,5,0) -> LOC|MLC_37 | O619: =VLOOKUP($A619,JV地区架构!$A:$F,6,0) -> Shandong | P619: =VLOOKUP($A619,JV数据源架构!$A:$F,5,0) -> SRC|DW_TMS | Q619: =VLOOKUP($A619,JV数据源架构!$A:$F,6,0) -> 通过DW上报TA（TMS）
A620: 00871 | B620: 马鞍山市郑蒲港新区港能投光伏有限公司 | C620: 马鞍山市郑蒲港新区港能投光伏有限公司 | D620: CNY | G620: PVZPJV | H620: =COUNTIF(JV映射!$C:$C,$A620) -> 1 | I620: {=_xlfn.IFNA(INDEX(JV映射!$A:$A,MATCH($A620,JV映射!$C:$C,0)),"")} -> 280 | J620: =COUNTIF(CTP映射!$C:$C,$A620) -> 1 | K620: {=_xlfn.IFNA(INDEX(CTP映射!A:A,MATCH($A620,CTP映射!C:C,0)),"")} -> 280 | L620: =VLOOKUP($A620,JV分部架构!$A:$F,5,0) -> ORG|MU_RENEWABLE_ENERGY_TSEL | M620: =VLOOKUP($A620,JV分部架构!$A:$F,6,0) -> Renewable Energy (TSEL) | N620: =VLOOKUP($A620,JV地区架构!$A:$F,5,0) -> LOC|MLC_34 | O620: =VLOOKUP($A620,JV地区架构!$A:$F,6,0) -> Anhui | P620: =VLOOKUP($A620,JV数据源架构!$A:$F,5,0) -> SRC|DW_TMS | Q620: =VLOOKUP($A620,JV数据源架构!$A:$F,6,0) -> 通过DW上报TA（TMS）
A621: 00872 | B621: 本溪港能投智慧能源有限公司 | C621: 本溪港能投智慧能源有限公司 | D621: CNY | G621: LNBXE | H621: =COUNTIF(JV映射!$C:$C,$A621) -> 1 | I621: {=_xlfn.IFNA(INDEX(JV映射!$A:$A,MATCH($A621,JV映射!$C:$C,0)),"")} -> 279 | J621: =COUNTIF(CTP映射!$C:$C,$A621) -> 1 | K621: {=_xlfn.IFNA(INDEX(CTP映射!A:A,MATCH($A621,CTP映射!C:C,0)),"")} -> 279 | L621: =VLOOKUP($A621,JV分部架构!$A:$F,5,0) -> ORG|MU_RENEWABLE_ENERGY_TSEL | M621: =VLOOKUP($A621,JV分部架构!$A:$F,6,0) -> Renewable Energy (TSEL) | N621: =VLOOKUP($A621,JV地区架构!$A:$F,5,0) -> LOC|MLC_21 | O621: =VLOOKUP($A621,JV地区架构!$A:$F,6,0) -> Liaoning | P621: =VLOOKUP($A621,JV数据源架构!$A:$F,5,0) -> SRC|DW_TMS | Q621: =VLOOKUP($A621,JV数据源架构!$A:$F,6,0) -> 通过DW上报TA（TMS）
A622: 00873 | B622: 青岛港能投清洁能源有限公司 | C622: 青岛港能投清洁能源有限公司 | D622: CNY | G622: SDQDLCE | H622: =COUNTIF(JV映射!$C:$C,$A622) -> 1 | I622: {=_xlfn.IFNA(INDEX(JV映射!$A:$A,MATCH($A622,JV映射!$C:$C,0)),"")} -> 370 | J622: =COUNTIF(CTP映射!$C:$C,$A622) -> 1 | K622: {=_xlfn.IFNA(INDEX(CTP映射!A:A,MATCH($A622,CTP映射!C:C,0)),"")} -> 370 | L622: =VLOOKUP($A622,JV分部架构!$A:$F,5,0) -> ORG|MU_RENEWABLE_ENERGY_TSEL | M622: =VLOOKUP($A622,JV分部架构!$A:$F,6,0) -> Renewable Energy (TSEL) | N622: =VLOOKUP($A622,JV地区架构!$A:$F,5,0) -> LOC|MLC_37 | O622: =VLOOKUP($A622,JV地区架构!$A:$F,6,0) -> Shandong | P622: =VLOOKUP($A622,JV数据源架构!$A:$F,5,0) -> SRC|DW_TMS | Q622: =VLOOKUP($A622,JV数据源架构!$A:$F,6,0) -> 通过DW上报TA（TMS）
A623: 00874 | B623: 溧阳恒电新能源科技有限公司 | C623: 溧阳恒电新能源科技有限公司 | D623: CNY | G623: PGLYJV | H623: =COUNTIF(JV映射!$C:$C,$A623) -> 1 | I623: {=_xlfn.IFNA(INDEX(JV映射!$A:$A,MATCH($A623,JV映射!$C:$C,0)),"")} -> 220 | J623: =COUNTIF(CTP映射!$C:$C,$A623) -> 1 | K623: {=_xlfn.IFNA(INDEX(CTP映射!A:A,MATCH($A623,CTP映射!C:C,0)),"")} -> 220 | L623: =VLOOKUP($A623,JV分部架构!$A:$F,5,0) -> ORG|MU_RENEWABLE_ENERGY_TSEL | M623: =VLOOKUP($A623,JV分部架构!$A:$F,6,0) -> Renewable Energy (TSEL) | N623: =VLOOKUP($A623,JV地区架构!$A:$F,5,0) -> LOC|MLC_32 | O623: =VLOOKUP($A623,JV地区架构!$A:$F,6,0) -> Jiangsu | P623: =VLOOKUP($A623,JV数据源架构!$A:$F,5,0) -> SRC|DW_TMS | Q623: =VLOOKUP($A623,JV数据源架构!$A:$F,6,0) -> 通过DW上报TA（TMS）
A624: 00875 | B624: 苏州光辰新能源科技有限公司 | C624: 苏州光辰新能源科技有限公司 | D624: CNY | G624: PGSUJV | H624: =COUNTIF(JV映射!$C:$C,$A624) -> 1 | I624: {=_xlfn.IFNA(INDEX(JV映射!$A:$A,MATCH($A624,JV映射!$C:$C,0)),"")} -> 246 | J624: =COUNTIF(CTP映射!$C:$C,$A624) -> 1 | K624: {=_xlfn.IFNA(INDEX(CTP映射!A:A,MATCH($A624,CTP映射!C:C,0)),"")} -> 246 | L624: =VLOOKUP($A624,JV分部架构!$A:$F,5,0) -> ORG|MU_RENEWABLE_ENERGY_TSEL | M624: =VLOOKUP($A624,JV分部架构!$A:$F,6,0) -> Renewable Energy (TSEL) | N624: =VLOOKUP($A624,JV地区架构!$A:$F,5,0) -> LOC|MLC_32 | O624: =VLOOKUP($A624,JV地区架构!$A:$F,6,0) -> Jiangsu | P624: =VLOOKUP($A624,JV数据源架构!$A:$F,5,0) -> SRC|DW_TMS | Q624: =VLOOKUP($A624,JV数据源架构!$A:$F,6,0) -> 通过DW上报TA（TMS）
A625: 00876 | B625: 郑州市港密新能源有限公司 | C625: 郑州市港密新能源有限公司 | D625: CNY | G625: HNZZGCE | H625: =COUNTIF(JV映射!$C:$C,$A625) -> 1 | I625: {=_xlfn.IFNA(INDEX(JV映射!$A:$A,MATCH($A625,JV映射!$C:$C,0)),"")} -> HNZZGCE | J625: =COUNTIF(CTP映射!$C:$C,$A625) -> 1 | K625: {=_xlfn.IFNA(INDEX(CTP映射!A:A,MATCH($A625,CTP映射!C:C,0)),"")} -> 366 | L625: =VLOOKUP($A625,JV分部架构!$A:$F,5,0) -> ORG|MU_RENEWABLE_ENERGY_TSEL | M625: =VLOOKUP($A625,JV分部架构!$A:$F,6,0) -> Renewable Energy (TSEL) | N625: =VLOOKUP($A625,JV地区架构!$A:$F,5,0) -> LOC|MLC_41 | O625: =VLOOKUP($A625,JV地区架构!$A:$F,6,0) -> Henan | P625: =VLOOKUP($A625,JV数据源架构!$A:$F,5,0) -> SRC|DW_TMS | Q625: =VLOOKUP($A625,JV数据源架构!$A:$F,6,0) -> 通过DW上报TA（TMS）
A626: 00877 | B626: 黄冈港能投智慧能源有限公司 | C626: 黄冈港能投智慧能源有限公司 | D626: CNY | G626: HBHGHCE | H626: =COUNTIF(JV映射!$C:$C,$A626) -> 1 | I626: {=_xlfn.IFNA(INDEX(JV映射!$A:$A,MATCH($A626,JV映射!$C:$C,0)),"")} -> 376 | J626: =COUNTIF(CTP映射!$C:$C,$A626) -> 1 | K626: {=_xlfn.IFNA(INDEX(CTP映射!A:A,MATCH($A626,CTP映射!C:C,0)),"")} -> 376 | L626: =VLOOKUP($A626,JV分部架构!$A:$F,5,0) -> ORG|MU_RENEWABLE_ENERGY_TSEL | M626: =VLOOKUP($A626,JV分部架构!$A:$F,6,0) -> Renewable Energy (TSEL) | N626: =VLOOKUP($A626,JV地区架构!$A:$F,5,0) -> LOC|MLC_42 | O626: =VLOOKUP($A626,JV地区架构!$A:$F,6,0) -> Hubei | P626: =VLOOKUP($A626,JV数据源架构!$A:$F,5,0) -> SRC|DW_TMS | Q626: =VLOOKUP($A626,JV数据源架构!$A:$F,6,0) -> 通过DW上报TA（TMS）
... A718: 01044 | B718: Lezhi Hong Kong and China Gas Company Limited | C718: 乐至港华燃气有限公司 | D718: CNY | G718: SCLZ | H718: =COUNTIF(JV映射!$C:$C,$A718) -> 1 | I718: {=_xlfn.IFNA(INDEX(JV映射!$A:$A,MATCH($A718,JV映射!$C:$C,0)),"")} -> 087 | J718: =COUNTIF(CTP映射!$C:$C,$A718) -> 1 | K718: {=_xlfn.IFNA(INDEX(CTP映射!A:A,MATCH($A718,CTP映射!C:C,0)),"")} -> 087 | L718: =VLOOKUP($A718,JV分部架构!$A:$F,5,0) -> ORG|MU_GAS_TSEL | M718: =VLOOKUP($A718,JV分部架构!$A:$F,6,0) -> City Gas (TSEL) | N718: =VLOOKUP($A718,JV地区架构!$A:$F,5,0) -> LOC|MLC_51 | O718: =VLOOKUP($A718,JV地区架构!$A:$F,6,0) -> Sichuan | P718: =VLOOKUP($A718,JV数据源架构!$A:$F,5,0) -> SRC|DW_TMS | Q718: =VLOOKUP($A718,JV数据源架构!$A:$F,6,0) -> 通过DW上报TA（TMS）
A719: 01045 | B719: 兴义港华舒适家科技服务有限公司 | C719: 兴义港华舒适家科技服务有限公司 | D719: CNY | H719: =COUNTIF(JV映射!$C:$C,$A719) -> 1 | I719: {=_xlfn.IFNA(INDEX(JV映射!$A:$A,MATCH($A719,JV映射!$C:$C,0)),"")} -> 20101 | J719: =COUNTIF(CTP映射!$C:$C,$A719) -> 1 | K719: {=_xlfn.IFNA(INDEX(CTP映射!A:A,MATCH($A719,CTP映射!C:C,0)),"")} -> 20101 | L719: =VLOOKUP($A719,JV分部架构!$A:$F,5,0) -> ORG|EB_PRC | M719: =VLOOKUP($A719,JV分部架构!$A:$F,6,0) -> Extended Business - Mainland | N719: =VLOOKUP($A719,JV地区架构!$A:$F,5,0) -> #N/A | O719: =VLOOKUP($A719,JV地区架构!$A:$F,6,0) -> #N/A | P719: =VLOOKUP($A719,JV数据源架构!$A:$F,5,0) -> SRC|DW_TMS | Q719: =VLOOKUP($A719,JV数据源架构!$A:$F,6,0) -> 通过DW上报TA（TMS）
A720: 01047 | B720: Hong Kong & China Gas (Yingkou) Limited | C720: 香港中华煤气（营口）有限公司 | D720: HKD | G720: HKYK | H720: =COUNTIF(JV映射!$C:$C,$A720) -> 0 | I720: {=_xlfn.IFNA(INDEX(JV映射!$A:$A,MATCH($A720,JV映射!$C:$C,0)),"")} | J720: =COUNTIF(CTP映射!$C:$C,$A720) -> 1 | K720: {=_xlfn.IFNA(INDEX(CTP映射!A:A,MATCH($A720,CTP映射!C:C,0)),"")} -> JYGLF0601 | L720: =VLOOKUP($A720,JV分部架构!$A:$F,5,0) -> ORG|OTHER | M720: =VLOOKUP($A720,JV分部架构!$A:$F,6,0) -> Other Businesses | N720: =VLOOKUP($A720,JV地区架构!$A:$F,5,0) -> LOC|BVI | O720: =VLOOKUP($A720,JV地区架构!$A:$F,6,0) -> BVI | P720: =VLOOKUP($A720,JV数据源架构!$A:$F,5,0) -> SRC|HK_SAP | Q720: =VLOOKUP($A720,JV数据源架构!$A:$F,6,0) -> SAP直接上报TA
A721: 01048 | B721: 港华舒适家（成都）科技服务有限公司 | C721: 港华舒适家（成都）科技服务有限公司 | D721: CNY | G721: TCHCD | H721: =COUNTIF(JV映射!$C:$C,$A721) -> 1 | I721: {=_xlfn.IFNA(INDEX(JV映射!$A:$A,MATCH($A721,JV映射!$C:$C,0)),"")} -> 201 | J721: =COUNTIF(CTP映射!$C:$C,$A721) -> 0 | K721: {=_xlfn.IFNA(INDEX(CTP映射!A:A,MATCH($A721,CTP映射!C:C,0)),"")} | L721: =VLOOKUP($A721,JV分部架构!$A:$F,5,0) -> ORG|EB_PRC | M721: =VLOOKUP($A721,JV分部架构!$A:$F,6,0) -> Extended Business - Mainland | N721: =VLOOKUP($A721,JV地区架构!$A:$F,5,0) -> LOC|MLC_51 | O721: =VLOOKUP($A721,JV地区架构!$A:$F,6,0) -> Sichuan | P721: =VLOOKUP($A721,JV数据源架构!$A:$F,5,0) -> #N/A | Q721: =VLOOKUP($A721,JV数据源架构!$A:$F,6,0) -> #N/A
A722: 01049 | B722: Yingkou Hong Kong and China Gas Co., Ltd. | C722: 营口港华燃气有限公司 | D722: CNY | G722: YKJV | H722: =COUNTIF(JV映射!$C:$C,$A722) -> 1 | I722: {=_xlfn.IFNA(INDEX(JV映射!$A:$A,MATCH($A722,JV映射!$C:$C,0)),"")} -> 022 | J722: =COUNTIF(CTP映射!$C:$C,$A722) -> 1 | K722: {=_xlfn.IFNA(INDEX(CTP映射!A:A,MATCH($A722,CTP映射!C:C,0)),"")} -> 022 | L722: =VLOOKUP($A722,JV分部架构!$A:$F,5,0) -> ORG|MU_GAS_TSEL | M722: =VLOOKUP($A722,JV分部架构!$A:$F,6,0) -> City Gas (TSEL) | N722: =VLOOKUP($A722,JV地区架构!$A:$F,5,0) -> LOC|MLC_21 | O722: =VLOOKUP($A722,JV地区架构!$A:$F,6,0) -> Liaoning | P722: =VLOOKUP($A722,JV数据源架构!$A:$F,5,0) -> SRC|DW_TMS | Q722: =VLOOKUP($A722,JV数据源架构!$A:$F,6,0) -> 通过DW上报TA（TMS）
A723: 01050 | B723: Ping Chang Hong Kong and China Gas Company Limited | C723: 平昌港华燃气有限公司 | D723: CNY | G723: SCPC | H723: =COUNTIF(JV映射!$C:$C,$A723) -> 1 | I723: {=_xlfn.IFNA(INDEX(JV映射!$A:$A,MATCH($A723,JV映射!$C:$C,0)),"")} -> 088 | J723: =COUNTIF(CTP映射!$C:$C,$A723) -> 1 | K723: {=_xlfn.IFNA(INDEX(CTP映射!A:A,MATCH($A723,CTP映射!C:C,0)),"")} -> 088 | L723: =VLOOKUP($A723,JV分部架构!$A:$F,5,0) -> ORG|MU_GAS_TSEL | M723: =VLOOKUP($A723,JV分部架构!$A:$F,6,0) -> City Gas (TSEL) | N723: =VLOOKUP($A723,JV地区架构!$A:$F,5,0) -> LOC|MLC_51 | O723: =VLOOKUP($A723,JV地区架构!$A:$F,6,0) -> Sichuan | P723: =VLOOKUP($A723,JV数据源架构!$A:$F,5,0) -> SRC|DW_TMS | Q723: =VLOOKUP($A723,JV数据源架构!$A:$F,6,0) -> 通过DW上报TA（TMS）
A724: 01051 | B724: Dalian Deta Towngas Co., Ltd. | C724: 大连德泰港华燃气股份有限公司 | D724: CNY | G724: DTJV | H724: =COUNTIF(JV映射!$C:$C,$A724) -> 1 | I724: {=_xlfn.IFNA(INDEX(JV映射!$A:$A,MATCH($A724,JV映射!$C:$C,0)),"")} -> DTJVR | J724: =COUNTIF(CTP映射!$C:$C,$A724) -> 1 | K724: {=_xlfn.IFNA(INDEX(CTP映射!A:A,MATCH($A724,CTP映射!C:C,0)),"")} -> 113 | L724: =VLOOKUP($A724,JV分部架构!$A:$F,5,0) -> ORG|MU_GAS_TSEL | M724: =VLOOKUP($A724,JV分部架构!$A:$F,6,0) -> City Gas (TSEL) | N724: =VLOOKUP($A724,JV地区架构!$A:$F,5,0) -> LOC|MLC_21 | O724: =VLOOKUP($A724,JV地区架构!$A:$F,6,0) -> Liaoning | P724: =VLOOKUP($A724,JV数据源架构!$A:$F,5,0) -> SRC|DW_TMS | Q724: =VLOOKUP($A724,JV数据源架构!$A:$F,6,0) -> 通过DW上报TA（TMS）
A725: 01052 | B725: Towngas (BVI) Holdings Limited | C725: 港华燃气（维尔京）控股有限公司 | D725: HKD | G725: TGHL | H725: =COUNTIF(JV映射!$C:$C,$A725) -> 0 | I725: {=_xlfn.IFNA(INDEX(JV映射!$A:$A,MATCH($A725,JV映射!$C:$C,0)),"")} | J725: =COUNTIF(CTP映射!$C:$C,$A725) -> 1 | K725: {=_xlfn.IFNA(INDEX(CTP映射!A:A,MATCH($A725,CTP映射!C:C,0)),"")} -> JYGLF0602 | L725: =VLOOKUP($A725,JV分部架构!$A:$F,5,0) -> ORG|OTHER | M725: =VLOOKUP($A725,JV分部架构!$A:$F,6,0) -> Other Businesses | N725: =VLOOKUP($A725,JV地区架构!$A:$F,5,0) -> LOC|BVI | O725: =VLOOKUP($A725,JV地区架构!$A:$F,6,0) -> BVI | P725: =VLOOKUP($A725,JV数据源架构!$A:$F,5,0) -> SRC|HK_SAP | Q725: =VLOOKUP($A725,JV数据源架构!$A:$F,6,0) -> SAP直接上报TA
A726: 01053 | B726: Hong Kong and China Gas (Dalian) Limited | C726: 香港中华煤气（大连）有限公司 | D726: HKD | G726: HKDL | H726: =COUNTIF(JV映射!$C:$C,$A726) -> 0 | I726: {=_xlfn.IFNA(INDEX(JV映射!$A:$A,MATCH($A726,JV映射!$C:$C,0)),"")} | J726: =COUNTIF(CTP映射!$C:$C,$A726) -> 1 | K726: {=_xlfn.IFNA(INDEX(CTP映射!A:A,MATCH($A726,CTP映射!C:C,0)),"")} -> JYGLF0597 | L726: =VLOOKUP($A726,JV分部架构!$A:$F,5,0) -> ORG|OTHER | M726: =VLOOKUP($A726,JV分部架构!$A:$F,6,0) -> Other Businesses | N726: =VLOOKUP($A726,JV地区架构!$A:$F,5,0) -> LOC|HK | O726: =VLOOKUP($A726,JV地区架构!$A:$F,6,0) -> Hong Kong | P726: =VLOOKUP($A726,JV数据源架构!$A:$F,5,0) -> SRC|HK_SAP | Q726: =VLOOKUP($A726,JV数据源架构!$A:$F,6,0) -> SAP直接上报TA
A727: 01055 | B727: Chengdu Gas Group Corporation Ltd. | C727: 成都燃气集团股份有限公司 | D727: CNY | H727: =COUNTIF(JV映射!$C:$C,$A727) -> 1 | I727: {=_xlfn.IFNA(INDEX(JV映射!$A:$A,MATCH($A727,JV映射!$C:$C,0)),"")} -> 092 | J727: =COUNTIF(CTP映射!$C:$C,$A727) -> 1 | K727: {=_xlfn.IFNA(INDEX(CTP映射!A:A,MATCH($A727,CTP映射!C:C,0)),"")} -> JYGLF0007 | L727: =VLOOKUP($A727,JV分部架构!$A:$F,5,0) -> ORG|MU_GAS_TSEL | M727: =VLOOKUP($A727,JV分部架构!$A:$F,6,0) -> City Gas (TSEL) | N727: =VLOOKUP($A727,JV地区架构!$A:$F,5,0) -> LOC|MLC_51 | O727: =VLOOKUP($A727,JV地区架构!$A:$F,6,0) -> Sichuan | P727: =VLOOKUP($A727,JV数据源架构!$A:$F,5,0) -> #N/A | Q727: =VLOOKUP($A727,JV数据源架构!$A:$F,6,0) -> #N/A
A728: 01056 | B728: Dalian Changxing Hong Kong and China Gas Co. Ltd. | C728: 大连长兴港华燃气有限公司 | D728: CNY | G728: DLCXJV | H728: =COUNTIF(JV映射!$C:$C,$A728) -> 1 | I728: {=_xlfn.IFNA(INDEX(JV映射!$A:$A,MATCH($A728,JV映射!$C:$C,0)),"")} -> 024 | J728: =COUNTIF(CTP映射!$C:$C,$A728) -> 1 | K728: {=_xlfn.IFNA(INDEX(CTP映射!A:A,MATCH($A728,CTP映射!C:C,0)),"")} -> 024 | L728: =VLOOKUP($A728,JV分部架构!$A:$F,5,0) -> ORG|MU_GAS_TSEL | M728: =VLOOKUP($A728,JV分部架构!$A:$F,6,0) -> City Gas (TSEL) | N728: =VLOOKUP($A728,JV地区架构!$A:$F,5,0) -> LOC|MLC_21 | O728: =VLOOKUP($A728,JV地区架构!$A:$F,6,0) -> Liaoning | P728: =VLOOKUP($A728,JV数据源架构!$A:$F,5,0) -> SRC|DW_TMS | Q728: =VLOOKUP($A728,JV数据源架构!$A:$F,6,0) -> 通过DW上报TA（TMS）
A729: 01057 | B729: Weiyuan Hong Kong and China Gas Company Limited | C729: 威远港华燃气有限公司 | D729: CNY | G729: SCWY | H729: =COUNTIF(JV映射!$C:$C,$A729) -> 1 | I729: {=_xlfn.IFNA(INDEX(JV映射!$A:$A,MATCH($A729,JV映射!$C:$C,0)),"")} -> SCWY | J729: =COUNTIF(CTP映射!$C:$C,$A729) -> 1 | K729: {=_xlfn.IFNA(INDEX(CTP映射!A:A,MATCH($A729,CTP映射!C:C,0)),"")} -> 085 | L729: =VLOOKUP($A729,JV分部架构!$A:$F,5,0) -> ORG|MU_GAS_TSEL | M729: =VLOOKUP($A729,JV分部架构!$A:$F,6,0) -> City Gas (TSEL) | N729: =VLOOKUP($A729,JV地区架构!$A:$F,5,0) -> LOC|MLC_51 | O729: =VLOOKUP($A729,JV地区架构!$A:$F,6,0) -> Sichuan | P729: =VLOOKUP($A729,JV数据源架构!$A:$F,5,0) -> SRC|DW_TMS | Q729: =VLOOKUP($A729,JV数据源架构!$A:$F,6,0) -> 通过DW上报TA（TMS）
A730: 01059 | B730: 四川港华合纵能源有限公司 | C730: 四川港华合纵能源有限公司 | D730: CNY | G730: TSUEL | H730: =COUNTIF(JV映射!$C:$C,$A730) -> 1 | I730: {=_xlfn.IFNA(INDEX(JV映射!$A:$A,MATCH($A730,JV映射!$C:$C,0)),"")} -> TSUEL | J730: =COUNTIF(CTP映射!$C:$C,$A730) -> 1 | K730: {=_xlfn.IFNA(INDEX(CTP映射!A:A,MATCH($A730,CTP映射!C:C,0)),"")} -> 204 | L730: =VLOOKUP($A730,JV分部架构!$A:$F,5,0) -> ORG|MU_MS_TSEL | M730: =VLOOKUP($A730,JV分部架构!$A:$F,6,0) -> Midstream (TSEL) | N730: =VLOOKUP($A730,JV地区架构!$A:$F,5,0) -> LOC|MLC_51 | O730: =VLOOKUP($A730,JV地区架构!$A:$F,6,0) -> Sichuan | P730: =VLOOKUP($A730,JV数据源架构!$A:$F,5,0) -> SRC|DW_TMS | Q730: =VLOOKUP($A730,JV数据源架构!$A:$F,6,0) -> 通过DW上报TA（TMS）
A731: 01062 | B731: Peng Xi Hong Kong and China Gas Company Limited | C731: 蓬溪港华燃气有限公司 | D731: CNY | G731: SCPX | H731: =COUNTIF(JV映射!$C:$C,$A731) -> 1 | I731: {=_xlfn.IFNA(INDEX(JV映射!$A:$A,MATCH($A731,JV映射!$C:$C,0)),"")} -> 086 | J731: =COUNTIF(CTP映射!$C:$C,$A731) -> 1 | K731: {=_xlfn.IFNA(INDEX(CTP映射!A:A,MATCH($A731,CTP映射!C:C,0)),"")} -> 086 | L731: =VLOOKUP($A731,JV分部架构!$A:$F,5,0) -> ORG|MU_GAS_TSEL | M731: =VLOOKUP($A731,JV分部架构!$A:$F,6,0) -> City Gas (TSEL) | N731: =VLOOKUP($A731,JV地区架构!$A:$F,5,0) -> LOC|MLC_51 | O731: =VLOOKUP($A731,JV地区架构!$A:$F,6,0) -> Sichuan | P731: =VLOOKUP($A731,JV数据源架构!$A:$F,5,0) -> SRC|DW_TMS | Q731: =VLOOKUP($A731,JV数据源架构!$A:$F,6,0) -> 通过DW上报TA（TMS）
A732: 01063 | B732: Mei Shan Peng Shan Hong Kong and China Gas Company Limited | C732: 眉山市彭山港华燃气有限公司 | D732: CNY | G732: SCPS | H732: =COUNTIF(JV映射!$C:$C,$A732) -> 1 | I732: {=_xlfn.IFNA(INDEX(JV映射!$A:$A,MATCH($A732,JV映射!$C:$C,0)),"")} -> SCPS | J732: =COUNTIF(CTP映射!$C:$C,$A732) -> 1 | K732: {=_xlfn.IFNA(INDEX(CTP映射!A:A,MATCH($A732,CTP映射!C:C,0)),"")} -> 095 | L732: =VLOOKUP($A732,JV分部架构!$A:$F,5,0) -> ORG|MU_GAS_TSEL | M732: =VLOOKUP($A732,JV分部架构!$A:$F,6,0) -> City Gas (TSEL) | N732: =VLOOKUP($A732,JV地区架构!$A:$F,5,0) -> LOC|MLC_51 | O732: =VLOOKUP($A732,JV地区架构!$A:$F,6,0) -> Sichuan | P732: =VLOOKUP($A732,JV数据源架构!$A:$F,5,0) -> SRC|DW_TMS | Q732: =VLOOKUP($A732,JV数据源架构!$A:$F,6,0) -> 通过DW上报TA（TMS）
A733: 01067 | B733: Chengdu Xindu Hong Kong and China Gas Company Limited | C733: 成都新都港华燃气有限公司 | D733: CNY | G733: SCXD | H733: =COUNTIF(JV映射!$C:$C,$A733) -> 1 | I733: {=_xlfn.IFNA(INDEX(JV映射!$A:$A,MATCH($A733,JV映射!$C:$C,0)),"")} -> 100 | J733: =COUNTIF(CTP映射!$C:$C,$A733) -> 1 | K733: {=_xlfn.IFNA(INDEX(CTP映射!A:A,MATCH($A733,CTP映射!C:C,0)),"")} -> 100 | L733: =VLOOKUP($A733,JV分部架构!$A:$F,5,0) -> ORG|MU_GAS_TSEL | M733: =VLOOKUP($A733,JV分部架构!$A:$F,6,0) -> City Gas (TSEL) | N733: =VLOOKUP($A733,JV地区架构!$A:$F,5,0) -> LOC|MLC_51 | O733: =VLOOKUP($A733,JV地区架构!$A:$F,6,0) -> Sichuan | P733: =VLOOKUP($A733,JV数据源架构!$A:$F,5,0) -> SRC|DW_TMS | Q733: =VLOOKUP($A733,JV数据源架构!$A:$F,6,0) -> 通过DW上报TA（TMS）
A734: 01069 | B734: Hong Kong and China Gas (Zhumadian) Limited | C734: 香港中华煤气（驻马店）有限公司 | D734: HKD | G734: HKZM | H734: =COUNTIF(JV映射!$C:$C,$A734) -> 0 | I734: {=_xlfn.IFNA(INDEX(JV映射!$A:$A,MATCH($A734,JV映射!$C:$C,0)),"")} | J734: =COUNTIF(CTP映射!$C:$C,$A734) -> 1 | K734: {=_xlfn.IFNA(INDEX(CTP映射!A:A,MATCH($A734,CTP映射!C:C,0)),"")} -> JYGLF0005 | L734: =VLOOKUP($A734,JV分部架构!$A:$F,5,0) -> ORG|OTHER | M734: =VLOOKUP($A734,JV分部架构!$A:$F,6,0) -> Other Businesses | N734: =VLOOKUP($A734,JV地区架构!$A:$F,5,0) -> LOC|HK | O734: =VLOOKUP($A734,JV地区架构!$A:$F,6,0) -> Hong Kong | P734: =VLOOKUP($A734,JV数据源架构!$A:$F,5,0) -> SRC|HK_SAP | Q734: =VLOOKUP($A734,JV数据源架构!$A:$F,6,0) -> SAP直接上报TA
A735: 01070 | B735: Dalian Wafangdian Hong Kong and China Gas Company Limited | C735: 大连瓦房店港华燃气有限公司 | D735: CNY | G735: DLJY | H735: =COUNTIF(JV映射!$C:$C,$A735) -> 1 | I735: {=_xlfn.IFNA(INDEX(JV映射!$A:$A,MATCH($A735,JV映射!$C:$C,0)),"")} -> 030 | J735: =COUNTIF(CTP映射!$C:$C,$A735) -> 1 | K735: {=_xlfn.IFNA(INDEX(CTP映射!A:A,MATCH($A735,CTP映射!C:C,0)),"")} -> 030 | L735: =VLOOKUP($A735,JV分部架构!$A:$F,5,0) -> ORG|MU_GAS_TSEL | M735: =VLOOKUP($A735,JV分部架构!$A:$F,6,0) -> City Gas (TSEL) | N735: =VLOOKUP($A735,JV地区架构!$A:$F,5,0) -> LOC|MLC_21 | O735: =VLOOKUP($A735,JV地区架构!$A:$F,6,0) -> Liaoning | P735: =VLOOKUP($A735,JV数据源架构!$A:$F,5,0) -> SRC|DW_TMS | Q735: =VLOOKUP($A735,JV数据源架构!$A:$F,6,0) -> 通过DW上报TA（TMS）
A736: 01071 | B736: Towngas Natural Gas Sales Co., Ltd. | C736: 港华天然气销售有限公司 | D736: CNY | G736: TNGS | H736: =COUNTIF(JV映射!$C:$C,$A736) -> 1 | I736: {=_xlfn.IFNA(INDEX(JV映射!$A:$A,MATCH($A736,JV映射!$C:$C,0)),"")} -> 185 | J736: =COUNTIF(CTP映射!$C:$C,$A736) -> 2 | K736: {=_xlfn.IFNA(INDEX(CTP映射!A:A,MATCH($A736,CTP映射!C:C,0)),"")} -> 185 | L736: =VLOOKUP($A736,JV分部架构!$A:$F,5,0) -> ORG|MU_GAS_TSEL | M736: =VLOOKUP($A736,JV分部架构!$A:$F,6,0) -> City Gas (TSEL) | N736: =VLOOKUP($A736,JV地区架构!$A:$F,5,0) -> LOC|MLC_31 | O736: =VLOOKUP($A736,JV地区架构!$A:$F,6,0) -> Shanghai | P736: =VLOOKUP($A736,JV数据源架构!$A:$F,5,0) -> SRC|DW_TMS | Q736: =VLOOKUP($A736,JV数据源架构!$A:$F,6,0) -> 通过DW上报TA（TMS）
A737: 01072 | B737: Zhong Jiang Hong Kong and China Gas Company Limited | C737: 中江港华燃气有限公司 | D737: CNY | G737: SCZJ | H737: =COUNTIF(JV映射!$C:$C,$A737) -> 1 | I737: {=_xlfn.IFNA(INDEX(JV映射!$A:$A,MATCH($A737,JV映射!$C:$C,0)),"")} -> SCZJ | J737: =COUNTIF(CTP映射!$C:$C,$A737) -> 1 | K737: {=_xlfn.IFNA(INDEX(CTP映射!A:A,MATCH($A737,CTP映射!C:C,0)),"")} -> 093 | L737: =VLOOKUP($A737,JV分部架构!$A:$F,5,0) -> ORG|MU_GAS_TSEL | M737: =VLOOKUP($A737,JV分部架构!$A:$F,6,0) -> City Gas (TSEL) | N737: =VLOOKUP($A737,JV地区架构!$A:$F,5,0) -> LOC|MLC_51 | O737: =VLOOKUP($A737,JV地区架构!$A:$F,6,0) -> Sichuan | P737: =VLOOKUP($A737,JV数据源架构!$A:$F,5,0) -> SRC|DW_TMS | Q737: =VLOOKUP($A737,JV数据源架构!$A:$F,6,0) -> 通过DW上报TA（TMS）
A738: 01074 | B738: Towngas Investments Limited | C738: 港华燃气投资有限公司 | D738: CNY | G738: TCCL | H738: =COUNTIF(JV映射!$C:$C,$A738) -> 1 | I738: {=_xlfn.IFNA(INDEX(JV映射!$A:$A,MATCH($A738,JV映射!$C:$C,0)),"")} -> TGCI | J738: =COUNTIF(CTP映射!$C:$C,$A738) -> 4 | K738: {=_xlfn.IFNA(INDEX(CTP映射!A:A,MATCH($A738,CTP映射!C:C,0)),"")} -> 003 | L738: =VLOOKUP($A738,JV分部架构!$A:$F,5,0) -> ORG|OTHER | M738: =VLOOKUP($A738,JV分部架构!$A:$F,6,0) -> Other Businesses | N738: =VLOOKUP($A738,JV地区架构!$A:$F,5,0) -> LOC|MLC_44 | O738: =VLOOKUP($A738,JV地区架构!$A:$F,6,0) -> Guangdong | P738: =VLOOKUP($A738,JV数据源架构!$A:$F,5,0) -> SRC|DW_TMS | Q738: =VLOOKUP($A738,JV数据源架构!$A:$F,6,0) -> 通过DW上报TA（TMS）
A739: 01076 | B739: Chi Ping Hongkong & China Gas Co. Ltd. | C739: 茌平港华燃气有限公司 | D739: CNY | G739: SDCP | H739: =COUNTIF(JV映射!$C:$C,$A739) -> 1 | I739: {=_xlfn.IFNA(INDEX(JV映射!$A:$A,MATCH($A739,JV映射!$C:$C,0)),"")} -> 077 | J739: =COUNTIF(CTP映射!$C:$C,$A739) -> 1 | K739: {=_xlfn.IFNA(INDEX(CTP映射!A:A,MATCH($A739,CTP映射!C:C,0)),"")} -> 077 | L739: =VLOOKUP($A739,JV分部架构!$A:$F,5,0) -> ORG|MU_GAS_TSEL | M739: =VLOOKUP($A739,JV分部架构!$A:$F,6,0) -> City Gas (TSEL) | N739: =VLOOKUP($A739,JV地区架构!$A:$F,5,0) -> LOC|MLC_37 | O739: =VLOOKUP($A739,JV地区架构!$A:$F,6,0) -> Shandong | P739: =VLOOKUP($A739,JV数据源架构!$A:$F,5,0) -> SRC|DW_TMS | Q739: =VLOOKUP($A739,JV数据源架构!$A:$F,6,0) -> 通过DW上报TA（TMS）
... A779: 01158 | B779: Qinhuangdao Hong Kong & China Gas Co., Ltd. | C779: 秦皇岛港华燃气有限公司 | D779: CNY | G779: HBQHD | H779: =COUNTIF(JV映射!$C:$C,$A779) -> 1 | I779: {=_xlfn.IFNA(INDEX(JV映射!$A:$A,MATCH($A779,JV映射!$C:$C,0)),"")} -> 130 | J779: =COUNTIF(CTP映射!$C:$C,$A779) -> 1 | K779: {=_xlfn.IFNA(INDEX(CTP映射!A:A,MATCH($A779,CTP映射!C:C,0)),"")} -> 130 | L779: =VLOOKUP($A779,JV分部架构!$A:$F,5,0) -> ORG|MU_GAS_TSEL | M779: =VLOOKUP($A779,JV分部架构!$A:$F,6,0) -> City Gas (TSEL) | N779: =VLOOKUP($A779,JV地区架构!$A:$F,5,0) -> LOC|MLC_13 | O779: =VLOOKUP($A779,JV地区架构!$A:$F,6,0) -> Hebei | P779: =VLOOKUP($A779,JV数据源架构!$A:$F,5,0) -> SRC|DW_TMS | Q779: =VLOOKUP($A779,JV数据源架构!$A:$F,6,0) -> 通过DW上报TA（TMS）
A780: 01159 | B780: 内蒙古港华天然气有限公司 | C780: 内蒙古港华天然气有限公司 | D780: CNY | H780: =COUNTIF(JV映射!$C:$C,$A780) -> 0 | I780: {=_xlfn.IFNA(INDEX(JV映射!$A:$A,MATCH($A780,JV映射!$C:$C,0)),"")} | J780: =COUNTIF(CTP映射!$C:$C,$A780) -> 1 | K780: {=_xlfn.IFNA(INDEX(CTP映射!A:A,MATCH($A780,CTP映射!C:C,0)),"")} -> JYGLF0703 | L780: =VLOOKUP($A780,JV分部架构!$A:$F,5,0) -> ORG|MU_GAS_TSEL | M780: =VLOOKUP($A780,JV分部架构!$A:$F,6,0) -> City Gas (TSEL) | N780: =VLOOKUP($A780,JV地区架构!$A:$F,5,0) -> LOC|MLC_15 | O780: =VLOOKUP($A780,JV地区架构!$A:$F,6,0) -> Inner Mongoria | P780: =VLOOKUP($A780,JV数据源架构!$A:$F,5,0) -> #N/A | Q780: =VLOOKUP($A780,JV数据源架构!$A:$F,6,0) -> #N/A
A781: 01163 | B781: 内蒙古西部天然气包北管道有限公司 | C781: 内蒙古西部天然气包北管道有限公司 | D781: CNY | G781: N/A | H781: =COUNTIF(JV映射!$C:$C,$A781) -> 1 | I781: {=_xlfn.IFNA(INDEX(JV映射!$A:$A,MATCH($A781,JV映射!$C:$C,0)),"")} -> 404 | J781: =COUNTIF(CTP映射!$C:$C,$A781) -> 1 | K781: {=_xlfn.IFNA(INDEX(CTP映射!A:A,MATCH($A781,CTP映射!C:C,0)),"")} -> 404 | L781: =VLOOKUP($A781,JV分部架构!$A:$F,5,0) -> ORG|MU_MS_TSEL | M781: =VLOOKUP($A781,JV分部架构!$A:$F,6,0) -> Midstream (TSEL) | N781: =VLOOKUP($A781,JV地区架构!$A:$F,5,0) -> LOC|MLC_15 | O781: =VLOOKUP($A781,JV地区架构!$A:$F,6,0) -> Inner Mongoria | P781: =VLOOKUP($A781,JV数据源架构!$A:$F,5,0) -> SRC|DW_TMS | Q781: =VLOOKUP($A781,JV数据源架构!$A:$F,6,0) -> 通过DW上报TA（TMS）
A782: 01167 | B782: Qiqihar Xingqixiang Gas Company Limited | C782: 齐齐哈尔兴企祥燃气有限责任公司 | D782: CNY | G782: HLXQX | H782: =COUNTIF(JV映射!$C:$C,$A782) -> 1 | I782: {=_xlfn.IFNA(INDEX(JV映射!$A:$A,MATCH($A782,JV映射!$C:$C,0)),"")} -> HLXQX | J782: =COUNTIF(CTP映射!$C:$C,$A782) -> 1 | K782: {=_xlfn.IFNA(INDEX(CTP映射!A:A,MATCH($A782,CTP映射!C:C,0)),"")} -> 171 | L782: =VLOOKUP($A782,JV分部架构!$A:$F,5,0) -> ORG|MU_GAS_TSEL | M782: =VLOOKUP($A782,JV分部架构!$A:$F,6,0) -> City Gas (TSEL) | N782: =VLOOKUP($A782,JV地区架构!$A:$F,5,0) -> LOC|MLC_23 | O782: =VLOOKUP($A782,JV地区架构!$A:$F,6,0) -> Heilongjiang | P782: =VLOOKUP($A782,JV数据源架构!$A:$F,5,0) -> SRC|DW_TMS | Q782: =VLOOKUP($A782,JV数据源架构!$A:$F,6,0) -> 通过DW上报TA（TMS）
A783: 01169 | B783: Changchun Changgang Gas Co., Ltd | C783: 长春长港燃气有限公司 | D783: CNY | H783: =COUNTIF(JV映射!$C:$C,$A783) -> 1 | I783: {=_xlfn.IFNA(INDEX(JV映射!$A:$A,MATCH($A783,JV映射!$C:$C,0)),"")} -> 108 | J783: =COUNTIF(CTP映射!$C:$C,$A783) -> 1 | K783: {=_xlfn.IFNA(INDEX(CTP映射!A:A,MATCH($A783,CTP映射!C:C,0)),"")} -> 108 | L783: =VLOOKUP($A783,JV分部架构!$A:$F,5,0) -> ORG|MU_GAS_TSEL | M783: =VLOOKUP($A783,JV分部架构!$A:$F,6,0) -> City Gas (TSEL) | N783: =VLOOKUP($A783,JV地区架构!$A:$F,5,0) -> LOC|MLC_22 | O783: =VLOOKUP($A783,JV地区架构!$A:$F,6,0) -> Jilin | P783: =VLOOKUP($A783,JV数据源架构!$A:$F,5,0) -> SRC|DW_REPORT2 | Q783: =VLOOKUP($A783,JV数据源架构!$A:$F,6,0) -> 通过DW上报TA（国内用简表2）
A784: 01170 | B784: Changchun Gas Co., Ltd | C784: 长春燃气股份有限公司 | D784: CNY | G784: N/A | H784: =COUNTIF(JV映射!$C:$C,$A784) -> 0 | I784: {=_xlfn.IFNA(INDEX(JV映射!$A:$A,MATCH($A784,JV映射!$C:$C,0)),"")} | J784: =COUNTIF(CTP映射!$C:$C,$A784) -> 2 | K784: {=_xlfn.IFNA(INDEX(CTP映射!A:A,MATCH($A784,CTP映射!C:C,0)),"")} -> JYGLF0070 | L784: =VLOOKUP($A784,JV分部架构!$A:$F,5,0) -> ORG|OTHER | M784: =VLOOKUP($A784,JV分部架构!$A:$F,6,0) -> Other Businesses | N784: =VLOOKUP($A784,JV地区架构!$A:$F,5,0) -> LOC|MLC_22 | O784: =VLOOKUP($A784,JV地区架构!$A:$F,6,0) -> Jilin | P784: =VLOOKUP($A784,JV数据源架构!$A:$F,5,0) -> SRC|HK_REPORT | Q784: =VLOOKUP($A784,JV数据源架构!$A:$F,6,0) -> 香港团队手工输入TA（香港用简表）
A785: 01172 | B785: Siping Hong Kong & China Gas Company Limited | C785: 四平港华燃气有限公司 | D785: CNY | G785: JLSP | H785: =COUNTIF(JV映射!$C:$C,$A785) -> 1 | I785: {=_xlfn.IFNA(INDEX(JV映射!$A:$A,MATCH($A785,JV映射!$C:$C,0)),"")} -> 151 | J785: =COUNTIF(CTP映射!$C:$C,$A785) -> 1 | K785: {=_xlfn.IFNA(INDEX(CTP映射!A:A,MATCH($A785,CTP映射!C:C,0)),"")} -> 151 | L785: =VLOOKUP($A785,JV分部架构!$A:$F,5,0) -> ORG|MU_GAS_TSEL | M785: =VLOOKUP($A785,JV分部架构!$A:$F,6,0) -> City Gas (TSEL) | N785: =VLOOKUP($A785,JV地区架构!$A:$F,5,0) -> LOC|MLC_22 | O785: =VLOOKUP($A785,JV地区架构!$A:$F,6,0) -> Jilin | P785: =VLOOKUP($A785,JV数据源架构!$A:$F,5,0) -> SRC|DW_TMS | Q785: =VLOOKUP($A785,JV数据源架构!$A:$F,6,0) -> 通过DW上报TA（TMS）
A786: 01173 | B786: Heilongjiang Hong Kong & China Lianfu New Energy Company Limited | C786: 黑龙江港华联孚能源有限公司 | D786: CNY | G786: HLJLF | H786: =COUNTIF(JV映射!$C:$C,$A786) -> 1 | I786: {=_xlfn.IFNA(INDEX(JV映射!$A:$A,MATCH($A786,JV映射!$C:$C,0)),"")} -> 148 | J786: =COUNTIF(CTP映射!$C:$C,$A786) -> 1 | K786: {=_xlfn.IFNA(INDEX(CTP映射!A:A,MATCH($A786,CTP映射!C:C,0)),"")} -> 148 | L786: =VLOOKUP($A786,JV分部架构!$A:$F,5,0) -> ORG|MU_GAS_TSEL | M786: =VLOOKUP($A786,JV分部架构!$A:$F,6,0) -> City Gas (TSEL) | N786: =VLOOKUP($A786,JV地区架构!$A:$F,5,0) -> LOC|MLC_23 | O786: =VLOOKUP($A786,JV地区架构!$A:$F,6,0) -> Heilongjiang | P786: =VLOOKUP($A786,JV数据源架构!$A:$F,5,0) -> SRC|DW_TMS | Q786: =VLOOKUP($A786,JV数据源架构!$A:$F,6,0) -> 通过DW上报TA（TMS）
A787: 01178 | B787: Gongzhuling Hong Kong and China Gas Company Limited | C787: 公主岭港华燃气有限公司 | D787: CNY | G787: JLGZL | H787: =COUNTIF(JV映射!$C:$C,$A787) -> 1 | I787: {=_xlfn.IFNA(INDEX(JV映射!$A:$A,MATCH($A787,JV映射!$C:$C,0)),"")} -> JLGZL | J787: =COUNTIF(CTP映射!$C:$C,$A787) -> 2 | K787: {=_xlfn.IFNA(INDEX(CTP映射!A:A,MATCH($A787,CTP映射!C:C,0)),"")} -> 023 | L787: =VLOOKUP($A787,JV分部架构!$A:$F,5,0) -> ORG|MU_GAS_TSEL | M787: =VLOOKUP($A787,JV分部架构!$A:$F,6,0) -> City Gas (TSEL) | N787: =VLOOKUP($A787,JV地区架构!$A:$F,5,0) -> LOC|MLC_22 | O787: =VLOOKUP($A787,JV地区架构!$A:$F,6,0) -> Jilin | P787: =VLOOKUP($A787,JV数据源架构!$A:$F,5,0) -> SRC|DW_TMS | Q787: =VLOOKUP($A787,JV数据源架构!$A:$F,6,0) -> 通过DW上报TA（TMS）
A788: 01181 | B788: C-Tech Laundry Investment Company Limited | C788: 卓惠洗涤投资有限公司 | D788: CNY | G788: CTLI | H788: =COUNTIF(JV映射!$C:$C,$A788) -> 0 | I788: {=_xlfn.IFNA(INDEX(JV映射!$A:$A,MATCH($A788,JV映射!$C:$C,0)),"")} | J788: =COUNTIF(CTP映射!$C:$C,$A788) -> 1 | K788: {=_xlfn.IFNA(INDEX(CTP映射!A:A,MATCH($A788,CTP映射!C:C,0)),"")} -> JYGLF0010 | L788: =VLOOKUP($A788,JV分部架构!$A:$F,5,0) -> ORG|OTHER | M788: =VLOOKUP($A788,JV分部架构!$A:$F,6,0) -> Other Businesses | N788: =VLOOKUP($A788,JV地区架构!$A:$F,5,0) -> LOC|HK | O788: =VLOOKUP($A788,JV地区架构!$A:$F,6,0) -> Hong Kong | P788: =VLOOKUP($A788,JV数据源架构!$A:$F,5,0) -> SRC|HK_SAP | Q788: =VLOOKUP($A788,JV数据源架构!$A:$F,6,0) -> SAP直接上报TA
A789: 01182 | B789: C-Tech Laundry Company Limited | C789: 卓惠洗涤有限公司 | D789: CNY | G789: CTLISZ | H789: =COUNTIF(JV映射!$C:$C,$A789) -> 1 | I789: {=_xlfn.IFNA(INDEX(JV映射!$A:$A,MATCH($A789,JV映射!$C:$C,0)),"")} -> 200 | J789: =COUNTIF(CTP映射!$C:$C,$A789) -> 1 | K789: {=_xlfn.IFNA(INDEX(CTP映射!A:A,MATCH($A789,CTP映射!C:C,0)),"")} -> 200 | L789: =VLOOKUP($A789,JV分部架构!$A:$F,5,0) -> ORG|MU_LAUNDRY_HCIL | M789: =VLOOKUP($A789,JV分部架构!$A:$F,6,0) -> Laundry (HCIL) | N789: =VLOOKUP($A789,JV地区架构!$A:$F,5,0) -> LOC|MLC | O789: =VLOOKUP($A789,JV地区架构!$A:$F,6,0) -> Mainland China | P789: =VLOOKUP($A789,JV数据源架构!$A:$F,5,0) -> SRC|DW_TMS | Q789: =VLOOKUP($A789,JV数据源架构!$A:$F,6,0) -> 通过DW上报TA（TMS）
A790: 01183 | B790: 潮州深能港华燃气有限公司 | C790: 潮州深能港华燃气有限公司 | D790: CNY | G790: CZSNJV | H790: =COUNTIF(JV映射!$C:$C,$A790) -> 1 | I790: {=_xlfn.IFNA(INDEX(JV映射!$A:$A,MATCH($A790,JV映射!$C:$C,0)),"")} -> CZSNJV | J790: =COUNTIF(CTP映射!$C:$C,$A790) -> 1 | K790: {=_xlfn.IFNA(INDEX(CTP映射!A:A,MATCH($A790,CTP映射!C:C,0)),"")} -> 411 | L790: =VLOOKUP($A790,JV分部架构!$A:$F,5,0) -> ORG|MU_GAS_TSEL | M790: =VLOOKUP($A790,JV分部架构!$A:$F,6,0) -> City Gas (TSEL) | N790: =VLOOKUP($A790,JV地区架构!$A:$F,5,0) -> LOC|MLC_44 | O790: =VLOOKUP($A790,JV地区架构!$A:$F,6,0) -> Guangdong | P790: =VLOOKUP($A790,JV数据源架构!$A:$F,5,0) -> SRC|DW_REPORT2 | Q790: =VLOOKUP($A790,JV数据源架构!$A:$F,6,0) -> 通过DW上报TA（国内用简表2）
A791: 01185 | B791: 港华紫荆农庄（句容）有限公司 | C791: 港华紫荆农庄（句容）有限公司 | D791: CNY | G791: AGJRJV | H791: =COUNTIF(JV映射!$C:$C,$A791) -> 1 | I791: {=_xlfn.IFNA(INDEX(JV映射!$A:$A,MATCH($A791,JV映射!$C:$C,0)),"")} -> 0510501 | J791: =COUNTIF(CTP映射!$C:$C,$A791) -> 1 | K791: {=_xlfn.IFNA(INDEX(CTP映射!A:A,MATCH($A791,CTP映射!C:C,0)),"")} -> 0510501 | L791: =VLOOKUP($A791,JV分部架构!$A:$F,5,0) -> ORG|EB_PRC | M791: =VLOOKUP($A791,JV分部架构!$A:$F,6,0) -> Extended Business - Mainland | N791: =VLOOKUP($A791,JV地区架构!$A:$F,5,0) -> LOC|MLC_32 | O791: =VLOOKUP($A791,JV地区架构!$A:$F,6,0) -> Jiangsu | P791: =VLOOKUP($A791,JV数据源架构!$A:$F,5,0) -> SRC|DW_TMS | Q791: =VLOOKUP($A791,JV数据源架构!$A:$F,6,0) -> 通过DW上报TA（TMS）
A792: 01274 | B792: EDA Energy Co Ltd | C792: EDA Energy Co Ltd | D792: HKD | G792: EDAE | H792: =COUNTIF(JV映射!$C:$C,$A792) -> 0 | I792: {=_xlfn.IFNA(INDEX(JV映射!$A:$A,MATCH($A792,JV映射!$C:$C,0)),"")} | J792: =COUNTIF(CTP映射!$C:$C,$A792) -> 0 | K792: {=_xlfn.IFNA(INDEX(CTP映射!A:A,MATCH($A792,CTP映射!C:C,0)),"")} | L792: =VLOOKUP($A792,JV分部架构!$A:$F,5,0) -> ORG|OTHER | M792: =VLOOKUP($A792,JV分部架构!$A:$F,6,0) -> Other Businesses | N792: =VLOOKUP($A792,JV地区架构!$A:$F,5,0) -> LOC|HK | O792: =VLOOKUP($A792,JV地区架构!$A:$F,6,0) -> Hong Kong | P792: =VLOOKUP($A792,JV数据源架构!$A:$F,5,0) -> #N/A | Q792: =VLOOKUP($A792,JV数据源架构!$A:$F,6,0) -> #N/A
A793: 01275 | B793: Fusion GH (Asia Pacific) Co Ltd | C793: Fusion GH (Asia Pacific) Co Ltd | D793: HKD | G793: FGAP | H793: =COUNTIF(JV映射!$C:$C,$A793) -> 0 | I793: {=_xlfn.IFNA(INDEX(JV映射!$A:$A,MATCH($A793,JV映射!$C:$C,0)),"")} | J793: =COUNTIF(CTP映射!$C:$C,$A793) -> 0 | K793: {=_xlfn.IFNA(INDEX(CTP映射!A:A,MATCH($A793,CTP映射!C:C,0)),"")} | L793: =VLOOKUP($A793,JV分部架构!$A:$F,5,0) -> ORG|OTHER | M793: =VLOOKUP($A793,JV分部架构!$A:$F,6,0) -> Other Businesses | N793: =VLOOKUP($A793,JV地区架构!$A:$F,5,0) -> LOC|HK | O793: =VLOOKUP($A793,JV地区架构!$A:$F,6,0) -> Hong Kong | P793: =VLOOKUP($A793,JV数据源架构!$A:$F,5,0) -> #N/A | Q793: =VLOOKUP($A793,JV数据源架构!$A:$F,6,0) -> #N/A
A794: 01276 | B794: Hansom Technology Limited | C794: Hansom Technology Limited | D794: HKD | G794: HANS | H794: =COUNTIF(JV映射!$C:$C,$A794) -> 0 | I794: {=_xlfn.IFNA(INDEX(JV映射!$A:$A,MATCH($A794,JV映射!$C:$C,0)),"")} | J794: =COUNTIF(CTP映射!$C:$C,$A794) -> 0 | K794: {=_xlfn.IFNA(INDEX(CTP映射!A:A,MATCH($A794,CTP映射!C:C,0)),"")} | L794: =VLOOKUP($A794,JV分部架构!$A:$F,5,0) -> ORG|OTHER | M794: =VLOOKUP($A794,JV分部架构!$A:$F,6,0) -> Other Businesses | N794: =VLOOKUP($A794,JV地区架构!$A:$F,5,0) -> LOC|BVI | O794: =VLOOKUP($A794,JV地区架构!$A:$F,6,0) -> BVI | P794: =VLOOKUP($A794,JV数据源架构!$A:$F,5,0) -> #N/A | Q794: =VLOOKUP($A794,JV数据源架构!$A:$F,6,0) -> #N/A
A795: 01281 | B795: Shanxi ECO Liyu Coalbed Methane Ltd | C795: Shanxi ECO Liyu Coalbed Methane Ltd | D795: HKD | G795: SELC | H795: =COUNTIF(JV映射!$C:$C,$A795) -> 0 | I795: {=_xlfn.IFNA(INDEX(JV映射!$A:$A,MATCH($A795,JV映射!$C:$C,0)),"")} | J795: =COUNTIF(CTP映射!$C:$C,$A795) -> 0 | K795: {=_xlfn.IFNA(INDEX(CTP映射!A:A,MATCH($A795,CTP映射!C:C,0)),"")} | L795: =VLOOKUP($A795,JV分部架构!$A:$F,5,0) -> ORG|HK_ECO | M795: =VLOOKUP($A795,JV分部架构!$A:$F,6,0) -> ECO | N795: =VLOOKUP($A795,JV地区架构!$A:$F,5,0) -> LOC|HK | O795: =VLOOKUP($A795,JV地区架构!$A:$F,6,0) -> Hong Kong | P795: =VLOOKUP($A795,JV数据源架构!$A:$F,5,0) -> #N/A | Q795: =VLOOKUP($A795,JV数据源架构!$A:$F,6,0) -> #N/A
... A813: 01420 | B813: 亳州皖华燃气有限公司 | C813: 亳州皖华燃气有限公司 | D813: CNY | G813: N/A | H813: =COUNTIF(JV映射!$C:$C,$A813) -> 0 | I813: {=_xlfn.IFNA(INDEX(JV映射!$A:$A,MATCH($A813,JV映射!$C:$C,0)),"")} | J813: =COUNTIF(CTP映射!$C:$C,$A813) -> 0 | K813: {=_xlfn.IFNA(INDEX(CTP映射!A:A,MATCH($A813,CTP映射!C:C,0)),"")} | L813: =VLOOKUP($A813,JV分部架构!$A:$F,5,0) -> ORG|OTHER | M813: =VLOOKUP($A813,JV分部架构!$A:$F,6,0) -> Other Businesses | N813: =VLOOKUP($A813,JV地区架构!$A:$F,5,0) -> LOC|MLC_34 | O813: =VLOOKUP($A813,JV地区架构!$A:$F,6,0) -> Anhui | P813: =VLOOKUP($A813,JV数据源架构!$A:$F,5,0) -> #N/A | Q813: =VLOOKUP($A813,JV数据源架构!$A:$F,6,0) -> #N/A
A814: 01439 | B814: 四川港华慧纵能源有限公司 | C814: 四川港华慧纵能源有限公司 | D814: CNY | H814: =COUNTIF(JV映射!$C:$C,$A814) -> 1 | I814: {=_xlfn.IFNA(INDEX(JV映射!$A:$A,MATCH($A814,JV映射!$C:$C,0)),"")} -> 290 | J814: =COUNTIF(CTP映射!$C:$C,$A814) -> 1 | K814: {=_xlfn.IFNA(INDEX(CTP映射!A:A,MATCH($A814,CTP映射!C:C,0)),"")} -> 290 | L814: =VLOOKUP($A814,JV分部架构!$A:$F,5,0) -> ORG|MU_RENEWABLE_ENERGY_TSEL | M814: =VLOOKUP($A814,JV分部架构!$A:$F,6,0) -> Renewable Energy (TSEL) | N814: =VLOOKUP($A814,JV地区架构!$A:$F,5,0) -> LOC|MLC_51 | O814: =VLOOKUP($A814,JV地区架构!$A:$F,6,0) -> Sichuan | P814: =VLOOKUP($A814,JV数据源架构!$A:$F,5,0) -> SRC|DW_TMS | Q814: =VLOOKUP($A814,JV数据源架构!$A:$F,6,0) -> 通过DW上报TA（TMS）
A815: 01447 | B815: 简阳港华燃气有限公司 | C815: 简阳港华燃气有限公司 | D815: CNY | G815: SCJY | H815: =COUNTIF(JV映射!$C:$C,$A815) -> 1 | I815: {=_xlfn.IFNA(INDEX(JV映射!$A:$A,MATCH($A815,JV映射!$C:$C,0)),"")} -> 094 | J815: =COUNTIF(CTP映射!$C:$C,$A815) -> 1 | K815: {=_xlfn.IFNA(INDEX(CTP映射!A:A,MATCH($A815,CTP映射!C:C,0)),"")} -> 094 | L815: =VLOOKUP($A815,JV分部架构!$A:$F,5,0) -> ORG|MU_GAS_TSEL | M815: =VLOOKUP($A815,JV分部架构!$A:$F,6,0) -> City Gas (TSEL) | N815: =VLOOKUP($A815,JV地区架构!$A:$F,5,0) -> LOC|MLC_51 | O815: =VLOOKUP($A815,JV地区架构!$A:$F,6,0) -> Sichuan | P815: =VLOOKUP($A815,JV数据源架构!$A:$F,5,0) -> SRC|DW_TMS | Q815: =VLOOKUP($A815,JV数据源架构!$A:$F,6,0) -> 通过DW上报TA（TMS）
A816: 01451 | B816: 新津永双港华燃气有限公司 | C816: 新津永双港华燃气有限公司 | D816: CNY | H816: =COUNTIF(JV映射!$C:$C,$A816) -> 0 | I816: {=_xlfn.IFNA(INDEX(JV映射!$A:$A,MATCH($A816,JV映射!$C:$C,0)),"")} | J816: =COUNTIF(CTP映射!$C:$C,$A816) -> 0 | K816: {=_xlfn.IFNA(INDEX(CTP映射!A:A,MATCH($A816,CTP映射!C:C,0)),"")} | L816: =VLOOKUP($A816,JV分部架构!$A:$F,5,0) -> ORG|MU_GAS_TSEL | M816: =VLOOKUP($A816,JV分部架构!$A:$F,6,0) -> City Gas (TSEL) | N816: =VLOOKUP($A816,JV地区架构!$A:$F,5,0) -> LOC|MLC_51 | O816: =VLOOKUP($A816,JV地区架构!$A:$F,6,0) -> Sichuan | P816: =VLOOKUP($A816,JV数据源架构!$A:$F,5,0) -> #N/A | Q816: =VLOOKUP($A816,JV数据源架构!$A:$F,6,0) -> #N/A
A817: 01516 | B817: 江门港华智慧能源有限公司 | C817: 江门港华智慧能源有限公司 | D817: CNY | G817: JMTSE | H817: =COUNTIF(JV映射!$C:$C,$A817) -> 1 | I817: {=_xlfn.IFNA(INDEX(JV映射!$A:$A,MATCH($A817,JV映射!$C:$C,0)),"")} -> 300 | J817: =COUNTIF(CTP映射!$C:$C,$A817) -> 1 | K817: {=_xlfn.IFNA(INDEX(CTP映射!A:A,MATCH($A817,CTP映射!C:C,0)),"")} -> 300 | L817: =VLOOKUP($A817,JV分部架构!$A:$F,5,0) -> ORG|MU_RENEWABLE_ENERGY_TSEL | M817: =VLOOKUP($A817,JV分部架构!$A:$F,6,0) -> Renewable Energy (TSEL) | N817: =VLOOKUP($A817,JV地区架构!$A:$F,5,0) -> LOC|MLC_44 | O817: =VLOOKUP($A817,JV地区架构!$A:$F,6,0) -> Guangdong | P817: =VLOOKUP($A817,JV数据源架构!$A:$F,5,0) -> SRC|DW_TMS | Q817: =VLOOKUP($A817,JV数据源架构!$A:$F,6,0) -> 通过DW上报TA（TMS）
A818: 01517 | B818: 株洲市国华智慧能源有限公司 (Disable) | C818: 株洲市国华智慧能源有限公司 (Disable) | D818: CNY | G818: HNZZE | H818: =COUNTIF(JV映射!$C:$C,$A818) -> 0 | I818: {=_xlfn.IFNA(INDEX(JV映射!$A:$A,MATCH($A818,JV映射!$C:$C,0)),"")} | J818: =COUNTIF(CTP映射!$C:$C,$A818) -> 0 | K818: {=_xlfn.IFNA(INDEX(CTP映射!A:A,MATCH($A818,CTP映射!C:C,0)),"")} | L818: =VLOOKUP($A818,JV分部架构!$A:$F,5,0) -> ORG|UPLOAD_ONLY | M818: =VLOOKUP($A818,JV分部架构!$A:$F,6,0) -> Upload only | N818: =VLOOKUP($A818,JV地区架构!$A:$F,5,0) -> LOC|MLC_43 | O818: =VLOOKUP($A818,JV地区架构!$A:$F,6,0) -> Hunan | P818: =VLOOKUP($A818,JV数据源架构!$A:$F,5,0) -> #N/A | Q818: =VLOOKUP($A818,JV数据源架构!$A:$F,6,0) -> #N/A
A819: 01518 | B819: 清远港能投智慧能源有限公司 | C819: 清远港能投智慧能源有限公司 | D819: CNY | G819: GDQCQCE | H819: =COUNTIF(JV映射!$C:$C,$A819) -> 1 | I819: {=_xlfn.IFNA(INDEX(JV映射!$A:$A,MATCH($A819,JV映射!$C:$C,0)),"")} -> 363 | J819: =COUNTIF(CTP映射!$C:$C,$A819) -> 3 | K819: {=_xlfn.IFNA(INDEX(CTP映射!A:A,MATCH($A819,CTP映射!C:C,0)),"")} -> 27303 | L819: =VLOOKUP($A819,JV分部架构!$A:$F,5,0) -> ORG|MU_RENEWABLE_ENERGY_TSEL | M819: =VLOOKUP($A819,JV分部架构!$A:$F,6,0) -> Renewable Energy (TSEL) | N819: =VLOOKUP($A819,JV地区架构!$A:$F,5,0) -> LOC|MLC_44 | O819: =VLOOKUP($A819,JV地区架构!$A:$F,6,0) -> Guangdong | P819: =VLOOKUP($A819,JV数据源架构!$A:$F,5,0) -> SRC|DW_TMS | Q819: =VLOOKUP($A819,JV数据源架构!$A:$F,6,0) -> 通过DW上报TA（TMS）
A820: 01519 | B820: 邵阳港能投新能源有限公司 | C820: 邵阳港能投新能源有限公司 | D820: CNY | G820: HNSYPE | H820: =COUNTIF(JV映射!$C:$C,$A820) -> 1 | I820: {=_xlfn.IFNA(INDEX(JV映射!$A:$A,MATCH($A820,JV映射!$C:$C,0)),"")} -> 406 | J820: =COUNTIF(CTP映射!$C:$C,$A820) -> 1 | K820: {=_xlfn.IFNA(INDEX(CTP映射!A:A,MATCH($A820,CTP映射!C:C,0)),"")} -> 406 | L820: =VLOOKUP($A820,JV分部架构!$A:$F,5,0) -> ORG|MU_RENEWABLE_ENERGY_TSEL | M820: =VLOOKUP($A820,JV分部架构!$A:$F,6,0) -> Renewable Energy (TSEL) | N820: =VLOOKUP($A820,JV地区架构!$A:$F,5,0) -> LOC|MLC_43 | O820: =VLOOKUP($A820,JV地区架构!$A:$F,6,0) -> Hunan | P820: =VLOOKUP($A820,JV数据源架构!$A:$F,5,0) -> SRC|DW_TMS | Q820: =VLOOKUP($A820,JV数据源架构!$A:$F,6,0) -> 通过DW上报TA（TMS）
A821: 01523 | B821: 揭阳港能投智慧能源有限公司 | C821: 江阴港能投智慧能源有限公司（合并） | D821: CNY | G821: GDJYPE | H821: =COUNTIF(JV映射!$C:$C,$A821) -> 0 | I821: {=_xlfn.IFNA(INDEX(JV映射!$A:$A,MATCH($A821,JV映射!$C:$C,0)),"")} | J821: =COUNTIF(CTP映射!$C:$C,$A821) -> 1 | K821: {=_xlfn.IFNA(INDEX(CTP映射!A:A,MATCH($A821,CTP映射!C:C,0)),"")} -> 413 | L821: =VLOOKUP($A821,JV分部架构!$A:$F,5,0) -> ORG|MU_RENEWABLE_ENERGY_TSEL | M821: =VLOOKUP($A821,JV分部架构!$A:$F,6,0) -> Renewable Energy (TSEL) | N821: =VLOOKUP($A821,JV地区架构!$A:$F,5,0) -> LOC|MLC_44 | O821: =VLOOKUP($A821,JV地区架构!$A:$F,6,0) -> Guangdong | P821: =VLOOKUP($A821,JV数据源架构!$A:$F,5,0) -> SRC|DW_TMS | Q821: =VLOOKUP($A821,JV数据源架构!$A:$F,6,0) -> 通过DW上报TA（TMS）
A822: 01525 | B822: 江阴港能投智慧能源有限公司（合并） | C822: 江阴港能投智慧能源有限公司（合并） | D822: CNY | H822: =COUNTIF(JV映射!$C:$C,$A822) -> 1 | I822: {=_xlfn.IFNA(INDEX(JV映射!$A:$A,MATCH($A822,JV映射!$C:$C,0)),"")} -> JSJYPE | J822: =COUNTIF(CTP映射!$C:$C,$A822) -> 1 | K822: {=_xlfn.IFNA(INDEX(CTP映射!A:A,MATCH($A822,CTP映射!C:C,0)),"")} -> 415 | L822: =VLOOKUP($A822,JV分部架构!$A:$F,5,0) -> ORG|MU_RENEWABLE_ENERGY_TSEL | M822: =VLOOKUP($A822,JV分部架构!$A:$F,6,0) -> Renewable Energy (TSEL) | N822: =VLOOKUP($A822,JV地区架构!$A:$F,5,0) -> LOC|MLC_32 | O822: =VLOOKUP($A822,JV地区架构!$A:$F,6,0) -> Jiangsu | P822: =VLOOKUP($A822,JV数据源架构!$A:$F,5,0) -> SRC|DW_TMS | Q822: =VLOOKUP($A822,JV数据源架构!$A:$F,6,0) -> 通过DW上报TA（TMS）
A823: 01539 | B823: 青岛市莱西港能清洁能源有限公司 | C823: 青岛市莱西港能清洁能源有限公司 | D823: CNY | G823: SDLXCE | H823: =COUNTIF(JV映射!$C:$C,$A823) -> 1 | I823: {=_xlfn.IFNA(INDEX(JV映射!$A:$A,MATCH($A823,JV映射!$C:$C,0)),"")} -> SDLXCE | J823: =COUNTIF(CTP映射!$C:$C,$A823) -> 1 | K823: {=_xlfn.IFNA(INDEX(CTP映射!A:A,MATCH($A823,CTP映射!C:C,0)),"")} -> 326 | L823: =VLOOKUP($A823,JV分部架构!$A:$F,5,0) -> ORG|MU_RENEWABLE_ENERGY_TSEL | M823: =VLOOKUP($A823,JV分部架构!$A:$F,6,0) -> Renewable Energy (TSEL) | N823: =VLOOKUP($A823,JV地区架构!$A:$F,5,0) -> LOC|MLC_37 | O823: =VLOOKUP($A823,JV地区架构!$A:$F,6,0) -> Shandong | P823: =VLOOKUP($A823,JV数据源架构!$A:$F,5,0) -> SRC|DW_TMS | Q823: =VLOOKUP($A823,JV数据源架构!$A:$F,6,0) -> 通过DW上报TA（TMS）
A824: 01540 | B824: 烟台市港能清洁能源有限公司（合并） | C824: 烟台市港能清洁能源有限公司（合并） | D824: CNY | H824: =COUNTIF(JV映射!$C:$C,$A824) -> 1 | I824: {=_xlfn.IFNA(INDEX(JV映射!$A:$A,MATCH($A824,JV映射!$C:$C,0)),"")} -> 32603 | J824: =COUNTIF(CTP映射!$C:$C,$A824) -> 2 | K824: {=_xlfn.IFNA(INDEX(CTP映射!A:A,MATCH($A824,CTP映射!C:C,0)),"")} -> 32603 | L824: =VLOOKUP($A824,JV分部架构!$A:$F,5,0) -> ORG|MU_RENEWABLE_ENERGY_TSEL | M824: =VLOOKUP($A824,JV分部架构!$A:$F,6,0) -> Renewable Energy (TSEL) | N824: =VLOOKUP($A824,JV地区架构!$A:$F,5,0) -> LOC|MLC_37 | O824: =VLOOKUP($A824,JV地区架构!$A:$F,6,0) -> Shandong | P824: =VLOOKUP($A824,JV数据源架构!$A:$F,5,0) -> SRC|DW_TMS | Q824: =VLOOKUP($A824,JV数据源架构!$A:$F,6,0) -> 通过DW上报TA（TMS）
A825: 01544 | B825: 宣城坤能新能源有限公司 | C825: 宣城坤能新能源有限公司 | D825: CNY | G825: AHXCKNE | H825: =COUNTIF(JV映射!$C:$C,$A825) -> 1 | I825: {=_xlfn.IFNA(INDEX(JV映射!$A:$A,MATCH($A825,JV映射!$C:$C,0)),"")} -> 32520 | J825: =COUNTIF(CTP映射!$C:$C,$A825) -> 1 | K825: {=_xlfn.IFNA(INDEX(CTP映射!A:A,MATCH($A825,CTP映射!C:C,0)),"")} -> 32520 | L825: =VLOOKUP($A825,JV分部架构!$A:$F,5,0) -> ORG|MU_RENEWABLE_ENERGY_TSEL | M825: =VLOOKUP($A825,JV分部架构!$A:$F,6,0) -> Renewable Energy (TSEL) | N825: =VLOOKUP($A825,JV地区架构!$A:$F,5,0) -> LOC|MLC_34 | O825: =VLOOKUP($A825,JV地区架构!$A:$F,6,0) -> Anhui | P825: =VLOOKUP($A825,JV数据源架构!$A:$F,5,0) -> SRC|DW_TMS | Q825: =VLOOKUP($A825,JV数据源架构!$A:$F,6,0) -> 通过DW上报TA（TMS）
A826: 01546 | B826: 开封捷迈新能源有限公司 | C826: 开封捷迈新能源有限公司 | D826: CNY | G826: HNKFJE | H826: =COUNTIF(JV映射!$C:$C,$A826) -> 1 | I826: {=_xlfn.IFNA(INDEX(JV映射!$A:$A,MATCH($A826,JV映射!$C:$C,0)),"")} -> 32547 | J826: =COUNTIF(CTP映射!$C:$C,$A826) -> 1 | K826: {=_xlfn.IFNA(INDEX(CTP映射!A:A,MATCH($A826,CTP映射!C:C,0)),"")} -> 32547 | L826: =VLOOKUP($A826,JV分部架构!$A:$F,5,0) -> ORG|MU_RENEWABLE_ENERGY_TSEL | M826: =VLOOKUP($A826,JV分部架构!$A:$F,6,0) -> Renewable Energy (TSEL) | N826: =VLOOKUP($A826,JV地区架构!$A:$F,5,0) -> LOC|MLC_41 | O826: =VLOOKUP($A826,JV地区架构!$A:$F,6,0) -> Henan | P826: =VLOOKUP($A826,JV数据源架构!$A:$F,5,0) -> SRC|DW_TMS | Q826: =VLOOKUP($A826,JV数据源架构!$A:$F,6,0) -> 通过DW上报TA（TMS）
A827: 01554 | B827: 宁夏环能新能源有限公司 | C827: 江阴港能投智慧能源有限公司（合并） | D827: CNY | G827: NXYCNE | H827: =COUNTIF(JV映射!$C:$C,$A827) -> 0 | I827: {=_xlfn.IFNA(INDEX(JV映射!$A:$A,MATCH($A827,JV映射!$C:$C,0)),"")} | J827: =COUNTIF(CTP映射!$C:$C,$A827) -> 1 | K827: {=_xlfn.IFNA(INDEX(CTP映射!A:A,MATCH($A827,CTP映射!C:C,0)),"")} -> 32566 | L827: =VLOOKUP($A827,JV分部架构!$A:$F,5,0) -> ORG|MU_RENEWABLE_ENERGY_TSEL | M827: =VLOOKUP($A827,JV分部架构!$A:$F,6,0) -> Renewable Energy (TSEL) | N827: =VLOOKUP($A827,JV地区架构!$A:$F,5,0) -> LOC|MLC_64 | O827: =VLOOKUP($A827,JV地区架构!$A:$F,6,0) -> Ningxia | P827: =VLOOKUP($A827,JV数据源架构!$A:$F,5,0) -> SRC|DW_TMS | Q827: =VLOOKUP($A827,JV数据源架构!$A:$F,6,0) -> 通过DW上报TA（TMS）
A828: 01555 | B828: 天津市滨海新区环聚新能源有限公司 | C828: 天津市滨海新区环聚新能源有限公司 | D828: CNY | G828: TJBHNE | H828: =COUNTIF(JV映射!$C:$C,$A828) -> 1 | I828: {=_xlfn.IFNA(INDEX(JV映射!$A:$A,MATCH($A828,JV映射!$C:$C,0)),"")} -> 32567 | J828: =COUNTIF(CTP映射!$C:$C,$A828) -> 1 | K828: {=_xlfn.IFNA(INDEX(CTP映射!A:A,MATCH($A828,CTP映射!C:C,0)),"")} -> 32567 | L828: =VLOOKUP($A828,JV分部架构!$A:$F,5,0) -> ORG|MU_RENEWABLE_ENERGY_TSEL | M828: =VLOOKUP($A828,JV分部架构!$A:$F,6,0) -> Renewable Energy (TSEL) | N828: =VLOOKUP($A828,JV地区架构!$A:$F,5,0) -> LOC|MLC_12 | O828: =VLOOKUP($A828,JV地区架构!$A:$F,6,0) -> Tianjing | P828: =VLOOKUP($A828,JV数据源架构!$A:$F,5,0) -> SRC|DW_TMS | Q828: =VLOOKUP($A828,JV数据源架构!$A:$F,6,0) -> 通过DW上报TA（TMS）
A829: 01556 | B829: 重庆玫克生智能科技有限公司 | C829: 重庆玫克生智能科技有限公司 | D829: CNY | G829: CQMKIE | H829: =COUNTIF(JV映射!$C:$C,$A829) -> 1 | I829: {=_xlfn.IFNA(INDEX(JV映射!$A:$A,MATCH($A829,JV映射!$C:$C,0)),"")} -> 32575 | J829: =COUNTIF(CTP映射!$C:$C,$A829) -> 1 | K829: {=_xlfn.IFNA(INDEX(CTP映射!A:A,MATCH($A829,CTP映射!C:C,0)),"")} -> 32575 | L829: =VLOOKUP($A829,JV分部架构!$A:$F,5,0) -> ORG|MU_RENEWABLE_ENERGY_TSEL | M829: =VLOOKUP($A829,JV分部架构!$A:$F,6,0) -> Renewable Energy (TSEL) | N829: =VLOOKUP($A829,JV地区架构!$A:$F,5,0) -> LOC|MLC_50 | O829: =VLOOKUP($A829,JV地区架构!$A:$F,6,0) -> Chongqing | P829: =VLOOKUP($A829,JV数据源架构!$A:$F,5,0) -> SRC|DW_TMS | Q829: =VLOOKUP($A829,JV数据源架构!$A:$F,6,0) -> 通过DW上报TA（TMS）
A830: 01682 | B830: 陕西港华智慧新能源有限公司 | C830: 陕西港华智慧新能源有限公司 | D830: CNY | G830: SXHDE | H830: =COUNTIF(JV映射!$C:$C,$A830) -> 1 | I830: {=_xlfn.IFNA(INDEX(JV映射!$A:$A,MATCH($A830,JV映射!$C:$C,0)),"")} -> 297 | J830: =COUNTIF(CTP映射!$C:$C,$A830) -> 1 | K830: {=_xlfn.IFNA(INDEX(CTP映射!A:A,MATCH($A830,CTP映射!C:C,0)),"")} -> 297 | L830: =VLOOKUP($A830,JV分部架构!$A:$F,5,0) -> ORG|MU_RENEWABLE_ENERGY_TSEL | M830: =VLOOKUP($A830,JV分部架构!$A:$F,6,0) -> Renewable Energy (TSEL) | N830: =VLOOKUP($A830,JV地区架构!$A:$F,5,0) -> LOC|MLC_61 | O830: =VLOOKUP($A830,JV地区架构!$A:$F,6,0) -> Shaanxi | P830: =VLOOKUP($A830,JV数据源架构!$A:$F,5,0) -> SRC|DW_TMS | Q830: =VLOOKUP($A830,JV数据源架构!$A:$F,6,0) -> 通过DW上报TA（TMS）
A831: 01797 | B831: 山东港燃经贸有限公司 | C831: 山东港燃经贸有限公司 | D831: CNY | G831: SDTJM | H831: =COUNTIF(JV映射!$C:$C,$A831) -> 1 | I831: {=_xlfn.IFNA(INDEX(JV映射!$A:$A,MATCH($A831,JV映射!$C:$C,0)),"")} -> 183 | J831: =COUNTIF(CTP映射!$C:$C,$A831) -> 1 | K831: {=_xlfn.IFNA(INDEX(CTP映射!A:A,MATCH($A831,CTP映射!C:C,0)),"")} -> 183 | L831: =VLOOKUP($A831,JV分部架构!$A:$F,5,0) -> ORG|MU_SUPP_HCIL | M831: =VLOOKUP($A831,JV分部架构!$A:$F,6,0) -> Gas Supply Chain (HCIL) | N831: =VLOOKUP($A831,JV地区架构!$A:$F,5,0) -> LOC|MLC_37 | O831: =VLOOKUP($A831,JV地区架构!$A:$F,6,0) -> Shandong | P831: =VLOOKUP($A831,JV数据源架构!$A:$F,5,0) -> SRC|DW_TMS | Q831: =VLOOKUP($A831,JV数据源架构!$A:$F,6,0) -> 通过DW上报TA（TMS）
A832: 01805 | B832: 株洲市国华智慧能源有限公司 | C832: 株洲市国华智慧能源有限公司 | D832: CNY | G832: ZZSSE | H832: =COUNTIF(JV映射!$C:$C,$A832) -> 1 | I832: {=_xlfn.IFNA(INDEX(JV映射!$A:$A,MATCH($A832,JV映射!$C:$C,0)),"")} -> 319 | J832: =COUNTIF(CTP映射!$C:$C,$A832) -> 1 | K832: {=_xlfn.IFNA(INDEX(CTP映射!A:A,MATCH($A832,CTP映射!C:C,0)),"")} -> 319 | L832: =VLOOKUP($A832,JV分部架构!$A:$F,5,0) -> ORG|MU_RENEWABLE_ENERGY_TSEL | M832: =VLOOKUP($A832,JV分部架构!$A:$F,6,0) -> Renewable Energy (TSEL) | N832: =VLOOKUP($A832,JV地区架构!$A:$F,5,0) -> LOC|MLC_43 | O832: =VLOOKUP($A832,JV地区架构!$A:$F,6,0) -> Hunan | P832: =VLOOKUP($A832,JV数据源架构!$A:$F,5,0) -> SRC|DW_TMS | Q832: =VLOOKUP($A832,JV数据源架构!$A:$F,6,0) -> 通过DW上报TA（TMS）
A833: 01806 | B833: 港华国际贸易 | C833: 港华国际贸易 | D833: CNY | G833: NYMY | H833: =COUNTIF(JV映射!$C:$C,$A833) -> 0 | I833: {=_xlfn.IFNA(INDEX(JV映射!$A:$A,MATCH($A833,JV映射!$C:$C,0)),"")} | J833: =COUNTIF(CTP映射!$C:$C,$A833) -> 0 | K833: {=_xlfn.IFNA(INDEX(CTP映射!A:A,MATCH($A833,CTP映射!C:C,0)),"")} | L833: =VLOOKUP($A833,JV分部架构!$A:$F,5,0) -> ORG|MU_SUPP_HCIL | M833: =VLOOKUP($A833,JV分部架构!$A:$F,6,0) -> Gas Supply Chain (HCIL) | N833: =VLOOKUP($A833,JV地区架构!$A:$F,5,0) -> LOC|MLC | O833: =VLOOKUP($A833,JV地区架构!$A:$F,6,0) -> Mainland China | P833: =VLOOKUP($A833,JV数据源架构!$A:$F,5,0) -> #N/A | Q833: =VLOOKUP($A833,JV数据源架构!$A:$F,6,0) -> #N/A
A834: 01809 | B834: 嘉祥易高能源有限公司 | C834: 嘉祥易高能源有限公司 | D834: CNY | G834: JXENJV | H834: =COUNTIF(JV映射!$C:$C,$A834) -> 0 | I834: {=_xlfn.IFNA(INDEX(JV映射!$A:$A,MATCH($A834,JV映射!$C:$C,0)),"")} | J834: =COUNTIF(CTP映射!$C:$C,$A834) -> 1 | K834: {=_xlfn.IFNA(INDEX(CTP映射!A:A,MATCH($A834,CTP映射!C:C,0)),"")} -> JYGLF0348 | L834: =VLOOKUP($A834,JV分部架构!$A:$F,5,0) -> ORG|N_ECO | M834: =VLOOKUP($A834,JV分部架构!$A:$F,6,0) -> ECO | N834: =VLOOKUP($A834,JV地区架构!$A:$F,5,0) -> LOC|MLC_37 | O834: =VLOOKUP($A834,JV地区架构!$A:$F,6,0) -> Shandong | P834: =VLOOKUP($A834,JV数据源架构!$A:$F,5,0) -> SRC|ECO_NC65 | Q834: =VLOOKUP($A834,JV数据源架构!$A:$F,6,0) -> 香港团队上载TA (NC6.5 TXT)
A835: 01810 | B835: 山西易高天星清洁能源有限公司 | C835: 山西易高天星清洁能源有限公司 | D835: CNY | G835: SXNCJV | H835: =COUNTIF(JV映射!$C:$C,$A835) -> 0 | I835: {=_xlfn.IFNA(INDEX(JV映射!$A:$A,MATCH($A835,JV映射!$C:$C,0)),"")} | J835: =COUNTIF(CTP映射!$C:$C,$A835) -> 1 | K835: {=_xlfn.IFNA(INDEX(CTP映射!A:A,MATCH($A835,CTP映射!C:C,0)),"")} -> JYGLF0358 | L835: =VLOOKUP($A835,JV分部架构!$A:$F,5,0) -> ORG|N_ECO | M835: =VLOOKUP($A835,JV分部架构!$A:$F,6,0) -> ECO | N835: =VLOOKUP($A835,JV地区架构!$A:$F,5,0) -> LOC|MLC_14 | O835: =VLOOKUP($A835,JV地区架构!$A:$F,6,0) -> Shanxi | P835: =VLOOKUP($A835,JV数据源架构!$A:$F,5,0) -> SRC|ECO_NC65 | Q835: =VLOOKUP($A835,JV数据源架构!$A:$F,6,0) -> 香港团队上载TA (NC6.5 TXT)
A836: 01811 | B836: 成武易高能源有限公司 | C836: 成武易高能源有限公司 | D836: CNY | G836: CMEEJV | H836: =COUNTIF(JV映射!$C:$C,$A836) -> 0 | I836: {=_xlfn.IFNA(INDEX(JV映射!$A:$A,MATCH($A836,JV映射!$C:$C,0)),"")} | J836: =COUNTIF(CTP映射!$C:$C,$A836) -> 1 | K836: {=_xlfn.IFNA(INDEX(CTP映射!A:A,MATCH($A836,CTP映射!C:C,0)),"")} -> JYGLF0512 | L836: =VLOOKUP($A836,JV分部架构!$A:$F,5,0) -> ORG|N_ECO | M836: =VLOOKUP($A836,JV分部架构!$A:$F,6,0) -> ECO | N836: =VLOOKUP($A836,JV地区架构!$A:$F,5,0) -> LOC|MLC_37 | O836: =VLOOKUP($A836,JV地区架构!$A:$F,6,0) -> Shandong | P836: =VLOOKUP($A836,JV数据源架构!$A:$F,5,0) -> SRC|ECO_NC65 | Q836: =VLOOKUP($A836,JV数据源架构!$A:$F,6,0) -> 香港团队上载TA (NC6.5 TXT)
... A841: 01826 | B841: 大连德泰港能投智慧能源有限公司 (Disable) | C841: 大连德泰港能投智慧能源有限公司 (Disable) | D841: CNY | G841: SEDLJV | H841: =COUNTIF(JV映射!$C:$C,$A841) -> 0 | I841: {=_xlfn.IFNA(INDEX(JV映射!$A:$A,MATCH($A841,JV映射!$C:$C,0)),"")} | J841: =COUNTIF(CTP映射!$C:$C,$A841) -> 0 | K841: {=_xlfn.IFNA(INDEX(CTP映射!A:A,MATCH($A841,CTP映射!C:C,0)),"")} | L841: =VLOOKUP($A841,JV分部架构!$A:$F,5,0) -> ORG|UPLOAD_ONLY | M841: =VLOOKUP($A841,JV分部架构!$A:$F,6,0) -> Upload only | N841: =VLOOKUP($A841,JV地区架构!$A:$F,5,0) -> LOC|MLC_21 | O841: =VLOOKUP($A841,JV地区架构!$A:$F,6,0) -> Liaoning | P841: =VLOOKUP($A841,JV数据源架构!$A:$F,5,0) -> #N/A | Q841: =VLOOKUP($A841,JV数据源架构!$A:$F,6,0) -> #N/A
A842: 01827 | B842: Towngas Lifestyle IP Limited | C842: Towngas Lifestyle IP Limited | D842: HKD | H842: =COUNTIF(JV映射!$C:$C,$A842) -> 0 | I842: {=_xlfn.IFNA(INDEX(JV映射!$A:$A,MATCH($A842,JV映射!$C:$C,0)),"")} | J842: =COUNTIF(CTP映射!$C:$C,$A842) -> 0 | K842: {=_xlfn.IFNA(INDEX(CTP映射!A:A,MATCH($A842,CTP映射!C:C,0)),"")} | L842: =VLOOKUP($A842,JV分部架构!$A:$F,5,0) -> ORG|EB_HK | M842: =VLOOKUP($A842,JV分部架构!$A:$F,6,0) -> Extended Business - Hong Kong | N842: =VLOOKUP($A842,JV地区架构!$A:$F,5,0) -> LOC|HK | O842: =VLOOKUP($A842,JV地区架构!$A:$F,6,0) -> Hong Kong | P842: =VLOOKUP($A842,JV数据源架构!$A:$F,5,0) -> SRC|HK_SAP | Q842: =VLOOKUP($A842,JV数据源架构!$A:$F,6,0) -> SAP直接上报TA
A843: 01828 | B843: Hong Kong Hydrogen Alliance Limited | C843: 香港氫能聯盟有限公司 | D843: HKD | H843: =COUNTIF(JV映射!$C:$C,$A843) -> 0 | I843: {=_xlfn.IFNA(INDEX(JV映射!$A:$A,MATCH($A843,JV映射!$C:$C,0)),"")} | J843: =COUNTIF(CTP映射!$C:$C,$A843) -> 1 | K843: {=_xlfn.IFNA(INDEX(CTP映射!A:A,MATCH($A843,CTP映射!C:C,0)),"")} -> 137 | L843: =VLOOKUP($A843,JV分部架构!$A:$F,5,0) -> ORG|HK_BUSINESS | M843: =VLOOKUP($A843,JV分部架构!$A:$F,6,0) -> HK Business | N843: =VLOOKUP($A843,JV地区架构!$A:$F,5,0) -> LOC|HK | O843: =VLOOKUP($A843,JV地区架构!$A:$F,6,0) -> Hong Kong | P843: =VLOOKUP($A843,JV数据源架构!$A:$F,5,0) -> #N/A | Q843: =VLOOKUP($A843,JV数据源架构!$A:$F,6,0) -> #N/A
A844: 01829 | B844: Novel Idea International Limited | C844: 星竣國際有限公司 | D844: HKD | H844: =COUNTIF(JV映射!$C:$C,$A844) -> 0 | I844: {=_xlfn.IFNA(INDEX(JV映射!$A:$A,MATCH($A844,JV映射!$C:$C,0)),"")} | J844: =COUNTIF(CTP映射!$C:$C,$A844) -> 1 | K844: {=_xlfn.IFNA(INDEX(CTP映射!A:A,MATCH($A844,CTP映射!C:C,0)),"")} -> 10602 | L844: =VLOOKUP($A844,JV分部架构!$A:$F,5,0) -> ORG|EB_HK | M844: =VLOOKUP($A844,JV分部架构!$A:$F,6,0) -> Extended Business - Hong Kong | N844: =VLOOKUP($A844,JV地区架构!$A:$F,5,0) -> LOC|HK | O844: =VLOOKUP($A844,JV地区架构!$A:$F,6,0) -> Hong Kong | P844: =VLOOKUP($A844,JV数据源架构!$A:$F,5,0) -> SRC|HK_SAP | Q844: =VLOOKUP($A844,JV数据源架构!$A:$F,6,0) -> SAP直接上报TA
A845: 01830 | B845: Towngas Energy Academy Holding Limited | C845: 港華能源研究院控股有限公司 | D845: HKD | H845: =COUNTIF(JV映射!$C:$C,$A845) -> 0 | I845: {=_xlfn.IFNA(INDEX(JV映射!$A:$A,MATCH($A845,JV映射!$C:$C,0)),"")} | J845: =COUNTIF(CTP映射!$C:$C,$A845) -> 1 | K845: {=_xlfn.IFNA(INDEX(CTP映射!A:A,MATCH($A845,CTP映射!C:C,0)),"")} -> 10902 | L845: =VLOOKUP($A845,JV分部架构!$A:$F,5,0) -> ORG|HK_BUSINESS | M845: =VLOOKUP($A845,JV分部架构!$A:$F,6,0) -> HK Business | N845: =VLOOKUP($A845,JV地区架构!$A:$F,5,0) -> LOC|HK | O845: =VLOOKUP($A845,JV地区架构!$A:$F,6,0) -> Hong Kong | P845: =VLOOKUP($A845,JV数据源架构!$A:$F,5,0) -> SRC|HK_SAP | Q845: =VLOOKUP($A845,JV数据源架构!$A:$F,6,0) -> SAP直接上报TA
A846: 01831 | B846: NovaNex Investments Holding Limited | C846: NovaNex Investments Holding Limited | D846: HKD | H846: =COUNTIF(JV映射!$C:$C,$A846) -> 0 | I846: {=_xlfn.IFNA(INDEX(JV映射!$A:$A,MATCH($A846,JV映射!$C:$C,0)),"")} | J846: =COUNTIF(CTP映射!$C:$C,$A846) -> 1 | K846: {=_xlfn.IFNA(INDEX(CTP映射!A:A,MATCH($A846,CTP映射!C:C,0)),"")} -> 10903 | L846: =VLOOKUP($A846,JV分部架构!$A:$F,5,0) -> ORG|HK_BUSINESS | M846: =VLOOKUP($A846,JV分部架构!$A:$F,6,0) -> HK Business | N846: =VLOOKUP($A846,JV地区架构!$A:$F,5,0) -> LOC|HK | O846: =VLOOKUP($A846,JV地区架构!$A:$F,6,0) -> Hong Kong | P846: =VLOOKUP($A846,JV数据源架构!$A:$F,5,0) -> SRC|HK_SAP | Q846: =VLOOKUP($A846,JV数据源架构!$A:$F,6,0) -> SAP直接上报TA
A847: 01832 | B847: NovaNex Investments Company Limited | C847: 保源環境投資有限公司 | D847: HKD | H847: =COUNTIF(JV映射!$C:$C,$A847) -> 0 | I847: {=_xlfn.IFNA(INDEX(JV映射!$A:$A,MATCH($A847,JV映射!$C:$C,0)),"")} | J847: =COUNTIF(CTP映射!$C:$C,$A847) -> 1 | K847: {=_xlfn.IFNA(INDEX(CTP映射!A:A,MATCH($A847,CTP映射!C:C,0)),"")} -> 10904 | L847: =VLOOKUP($A847,JV分部架构!$A:$F,5,0) -> ORG|HK_BUSINESS | M847: =VLOOKUP($A847,JV分部架构!$A:$F,6,0) -> HK Business | N847: =VLOOKUP($A847,JV地区架构!$A:$F,5,0) -> LOC|HK | O847: =VLOOKUP($A847,JV地区架构!$A:$F,6,0) -> Hong Kong | P847: =VLOOKUP($A847,JV数据源架构!$A:$F,5,0) -> SRC|HK_SAP | Q847: =VLOOKUP($A847,JV数据源架构!$A:$F,6,0) -> SAP直接上报TA
A848: 01833 | B848: Townlife Holding Company Limited | C848: 家域控股有限公司 | D848: HKD | H848: =COUNTIF(JV映射!$C:$C,$A848) -> 0 | I848: {=_xlfn.IFNA(INDEX(JV映射!$A:$A,MATCH($A848,JV映射!$C:$C,0)),"")} | J848: =COUNTIF(CTP映射!$C:$C,$A848) -> 1 | K848: {=_xlfn.IFNA(INDEX(CTP映射!A:A,MATCH($A848,CTP映射!C:C,0)),"")} -> 10905 | L848: =VLOOKUP($A848,JV分部架构!$A:$F,5,0) -> ORG|EB_HK | M848: =VLOOKUP($A848,JV分部架构!$A:$F,6,0) -> Extended Business - Hong Kong | N848: =VLOOKUP($A848,JV地区架构!$A:$F,5,0) -> LOC|HK | O848: =VLOOKUP($A848,JV地区架构!$A:$F,6,0) -> Hong Kong | P848: =VLOOKUP($A848,JV数据源架构!$A:$F,5,0) -> SRC|HK_SAP | Q848: =VLOOKUP($A848,JV数据源架构!$A:$F,6,0) -> SAP直接上报TA
...

Sheet JV分部架构
A1: Entity list | B1: Entity list - Description | C1: Hierarchy | D1: Hierarchy - Description | E1: Node | F1: Node - Description
A2: 00001 | B2: The Hong Kong and China Gas Company Limited | C2: ORG | D2: Entity-Segment | E2: ORG|HK_CORE | F2: Hong Kong Business
A3: 00002 | B3: Skyward Investments Limited | C3: ORG | D3: Entity-Segment | E3: ORG|HK_BUSINESS | F3: HK Business
A4: 00003 | B4: Brilliant World International Limited | C4: ORG | D4: Entity-Segment | E4: ORG|HK_BUSINESS | F4: HK Business
A5: 00004 | B5: Edonlite Holdings Limited | C5: ORG | D5: Entity-Segment | E5: ORG|HK_BUSINESS | F5: HK Business
A6: 00005 | B6: Primebay Investments Limited | C6: ORG | D6: Entity-Segment | E6: ORG|HK_BUSINESS | F6: HK Business
A7: 00006 | B7: China Guide Resources Limited | C7: ORG | D7: Entity-Segment | E7: ORG|HK_BUSINESS | F7: HK Business
A8: 00007 | B8: Smoothing Investment Limited | C8: ORG | D8: Entity-Segment | E8: ORG|HK_BUSINESS | F8: HK Business
A9: 00008 | B9: Quality Testing Services Limited | C9: ORG | D9: Entity-Segment | E9: ORG|HK_BUSINESS | F9: HK Business
A10: 00009 | B10: P-Tech Engineering Company Limited | C10: ORG | D10: Entity-Segment | E10: ORG|P_TECH | F10: P-Tech
A11: 00010 | B11: China Gas Company Limited | C11: ORG | D11: Entity-Segment | E11: ORG|HK_BUSINESS | F11: HK Business
A12: 00011 | B12: Hong Kong Gas Company Limited | C12: ORG | D12: Entity-Segment | E12: ORG|HK_BUSINESS | F12: HK Business
... A857: MA_00300-91 | B857: Hong Kong & China Gas Investment Limited(SZ OFFICE) | C857: ORG | D857: Entity-Segment | E857: ORG|MU | F857: Mainland Business

Sheet JV地区架构
A1: Entity list | B1: Entity list - Description | C1: Hierarchy | D1: Hierarchy - Description | E1: Node | F1: Node - Description
A2: 00001 | B2: The Hong Kong and China Gas Company Limited | C2: LOC | D2: Location | E2: LOC|HK | F2: Hong Kong
A3: 00002 | B3: Skyward Investments Limited | C3: LOC | D3: Location | E3: LOC|HK | F3: Hong Kong
A4: 00003 | B4: Brilliant World International Limited | C4: LOC | D4: Location | E4: LOC|BVI | F4: BVI
A5: 00004 | B5: Edonlite Holdings Limited | C5: LOC | D5: Location | E5: LOC|BVI | F5: BVI
A6: 00005 | B6: Primebay Investments Limited | C6: LOC | D6: Location | E6: LOC|BVI | F6: BVI
A7: 00006 | B7: China Guide Resources Limited | C7: LOC | D7: Location | E7: LOC|HK | F7: Hong Kong
A8: 00007 | B8: Smoothing Investment Limited | C8: LOC | D8: Location | E8: LOC|HK | F8: Hong Kong
A9: 00008 | B9: Quality Testing Services Limited | C9: LOC | D9: Location | E9: LOC|HK | F9: Hong Kong
A10: 00009 | B10: P-Tech Engineering Company Limited | C10: LOC | D10: Location | E10: LOC|HK | F10: Hong Kong
A11: 00010 | B11: China Gas Company Limited | C11: LOC | D11: Location | E11: LOC|HK | F11: Hong Kong
A12: 00011 | B12: Hong Kong Gas Company Limited | C12: LOC | D12: Location | E12: LOC|HK | F12: Hong Kong
... A841: 02278 | B841: 深圳港华慧能科技有限公司（合并） | C841: LOC | D841: Location | E841: LOC|MLC_44 | F841: Guangdong

Sheet JV数据源架构
A1: Entity list | B1: Entity list - Description | C1: Hierarchy | D1: Hierarchy - Description | E1: Node | F1: Node - Description
A2: 00001 | B2: The Hong Kong and China Gas Company Limited | C2: SRC | D2: Source | E2: SRC|HK_SAP | F2: SAP直接上报TA
A3: 00002 | B3: Skyward Investments Limited | C3: SRC | D3: Source | E3: SRC|HK_SAP | F3: SAP直接上报TA
A4: 00003 | B4: Brilliant World International Limited | C4: SRC | D4: Source | E4: SRC|HK_SAP | F4: SAP直接上报TA
A5: 00004 | B5: Edonlite Holdings Limited | C5: SRC | D5: Source | E5: SRC|HK_SAP | F5: SAP直接上报TA
A6: 00005 | B6: Primebay Investments Limited | C6: SRC | D6: Source | E6: SRC|HK_SAP | F6: SAP直接上报TA
A7: 00006 | B7: China Guide Resources Limited | C7: SRC | D7: Source | E7: SRC|HK_SAP | F7: SAP直接上报TA
A8: 00007 | B8: Smoothing Investment Limited | C8: SRC | D8: Source | E8: SRC|HK_SAP | F8: SAP直接上报TA
A9: 00008 | B9: Quality Testing Services Limited | C9: SRC | D9: Source | E9: SRC|HK_SAP | F9: SAP直接上报TA
A10: 00009 | B10: P-Tech Engineering Company Limited | C10: SRC | D10: Source | E10: SRC|HK_SAP | F10: SAP直接上报TA
A11: 00010 | B11: China Gas Company Limited | C11: SRC | D11: Source | E11: SRC|HK_SAP | F11: SAP直接上报TA
A12: 00011 | B12: Hong Kong Gas Company Limited | C12: SRC | D12: Source | E12: SRC|HK_SAP | F12: SAP直接上报TA
... A833: MA_00300-91 | B833: Hong Kong & China Gas Investment Limited(SZ OFFICE) | C833: SRC | D833: Source | E833: SRC|XX_DUMMY | F833: Dummy Entity

Sheet JV映射
A1: Input 1 - TMS_ENTI | B1: Description Input 1 - TMS_ENTI | C1: Output 1 - TA_ENTI | D1: Description Output 1 - TA_ENTI | E1: mat
A2: 00209 | C2: 00375 | D2: 名气家投资有限公司 | E2: =VLOOKUP(C2,CTP映射!C:D,2,FALSE) -> 名气家投资有限公司
A3: 00210 | C3: 00331 | D3: 港华国际能源贸易有限公司 | E3: =VLOOKUP(C3,CTP映射!C:D,2,FALSE) -> 港华国际能源贸易有限公司
A4: 006 | C4: 00930 | D4: 安庆港华燃气有限公司 | E4: =VLOOKUP(C4,CTP映射!C:D,2,FALSE) -> 安庆港华燃气有限公司
A5: 007 | C5: 00285 | D5: 安徽省天然气开发股份有限公司 | E5: =VLOOKUP(C5,CTP映射!C:D,2,FALSE) -> 安徽省天然气开发股份有限公司
A6: 009 | C6: 00968 | D6: 黄山港华燃气有限公司 | E6: =VLOOKUP(C6,CTP映射!C:D,2,FALSE) -> 黄山港华燃气有限公司
A7: 010 | C7: 00967 | D7: 黄山太平港华燃气有限公司 | E7: =VLOOKUP(C7,CTP映射!C:D,2,FALSE) -> 黄山太平港华燃气有限公司
A8: 011 | C8: 00969 | D8: 黄山徽州港华燃气有限公司 | E8: =VLOOKUP(C8,CTP映射!C:D,2,FALSE) -> 黄山徽州港华燃气有限公司
A9: 012 | C9: 00918 | D9: 马鞍山博望港华燃气有限公司 | E9: =VLOOKUP(C9,CTP映射!C:D,2,FALSE) -> 马鞍山博望港华燃气有限公司
A10: 014 | C10: 00275 | D10: 张家港港华燃气有限公司 | E10: =VLOOKUP(C10,CTP映射!C:D,2,FALSE) -> 张家港港华燃气有限公司
A11: 015 | C11: 00287 | D11: 吴江港华燃气有限公司 | E11: =VLOOKUP(C11,CTP映射!C:D,2,FALSE) -> 吴江港华燃气有限公司
A12: 01902 | C12: 00607 | D12: 铁岭港能投智慧能源有限公司 | E12: =VLOOKUP(C12,CTP映射!C:D,2,FALSE) -> 铁岭港能投智慧能源有限公司
A13: 022 | C13: 01049 | D13: 营口港华燃气有限公司 | E13: =VLOOKUP(C13,CTP映射!C:D,2,FALSE) -> 营口港华燃气有限公司
... A433: ZSJV | C433: 00271 | D433: 中山港华燃气有限公司 | E433: =VLOOKUP(C433,CTP映射!C:D,2,FALSE) -> 中山港华燃气有限公司

Sheet CTP映射
A1: Input 1 - TMS_CTP | B1: Description Input 1 - TMS_CTP | C1: Output 1 - TA_CTP | D1: Description Output 1 - TA_CTP
A2: 002 | C2: 00300 | D2: 港华投资有限公司
A3: 00201 | C3: 00378 | D3: 卓锐智高（武汉）科技有限公司
A4: 002012 | C4: 00344 | D4: 宿迁港能投光伏有限公司
A5: 00201201 | C5: 00372 | D5: 宿迁迅途能源有限公司
A6: 00201202 | C6: 00383 | D6: 宿迁鑫洲新能源有限公司 | F6: 1865
A7: 00202 | C7: 00322 | D7: 广州港华燃气科技服务有限公司 | F7: 432
A8: 00203 | C8: 00321 | D8: 港华紫荆燃具（深圳）有限公司
A9: 00204 | C9: 00310 | D9: 沈阳三全工程监理咨询有限公司
A10: 0020406 | C10: 01720 | D10: 沈阳三全工程监理咨询有限公司徐州分公司
A11: 00205 | C11: 00324 | D11: 深圳市燃气用具有限公司
A12: 00206 | C12: 00325 | D12: 中新苏州工业园区开发集团股份有限公司
A13: 00209 | C13: 00328 | D13: 名气家信息服务有限公司
A14: 0020902 | C14: 01198 | D14: 名气家（上海）数字科技有限公司
A15: 0020903 | C15: 01245 | D15: 港华到家（广东）信息技术有限公司
A16: 002090301 | C16: 02236 | D16: 清远名气家生活服务有限公司
A17: 002090302 | C17: 01743 | D17: 港华到家（广东）信息技术有限公司广州番禺桥南店
A18: 002090303 | C18: 01744 | D18: 港华到家（广东）信息技术有限公司广州东永天琅店
A19: 002090304 | C19: 01247 | D19: 港华到家（中山）信息科技有限公司
... A1866: SW00806 | C1866: 00360 | D1866: 江苏道胜市容环境服务有限公司

Sheet 公司清单
A1: Company List | F1: 与JV的关系
A2: Code | B2: English Description | C2: 中文 description | D2: Start date | E2: End date | F2: 是否JV/CTP | G2: 归属Entity/JV | H2: 归属Entity/JV名称
A3: 00001 | B3: The Hong Kong and China Gas Company Limited | C3: 香港中华煤气有限公司 | F3: =_xlfn.IFNA(IF(MATCH(A3,'JV and CTP清单'!A:A,0)>0,"是",""),"否") -> 是 | G3: =_xlfn.IFNA(VLOOKUP($A3,公司与JV对应关系!$A:$D,3,0),"") | H3: =_xlfn.IFNA(VLOOKUP($A3,公司与JV对应关系!$A:$D,4,0),"")
A4: 00002 | B4: Skyward Investments Limited | C4: Skyward Investments Limited | F4: =_xlfn.IFNA(IF(MATCH(A4,'JV and CTP清单'!A:A,0)>0,"是",""),"否") -> 是 | G4: =_xlfn.IFNA(VLOOKUP($A4,公司与JV对应关系!$A:$D,3,0),"") | H4: =_xlfn.IFNA(VLOOKUP($A4,公司与JV对应关系!$A:$D,4,0),"")
A5: 00003 | B5: Brilliant World International Limited | C5: Brilliant World International Limited | F5: =_xlfn.IFNA(IF(MATCH(A5,'JV and CTP清单'!A:A,0)>0,"是",""),"否") -> 是 | G5: =_xlfn.IFNA(VLOOKUP($A5,公司与JV对应关系!$A:$D,3,0),"") | H5: =_xlfn.IFNA(VLOOKUP($A5,公司与JV对应关系!$A:$D,4,0),"")
A6: 00004 | B6: Edonlite Holdings Limited | C6: Edonlite Holdings Limited | F6: =_xlfn.IFNA(IF(MATCH(A6,'JV and CTP清单'!A:A,0)>0,"是",""),"否") -> 是 | G6: =_xlfn.IFNA(VLOOKUP($A6,公司与JV对应关系!$A:$D,3,0),"") | H6: =_xlfn.IFNA(VLOOKUP($A6,公司与JV对应关系!$A:$D,4,0),"")
A7: 00005 | B7: Primebay Investments Limited | C7: Primebay Investments Limited | F7: =_xlfn.IFNA(IF(MATCH(A7,'JV and CTP清单'!A:A,0)>0,"是",""),"否") -> 是 | G7: =_xlfn.IFNA(VLOOKUP($A7,公司与JV对应关系!$A:$D,3,0),"") | H7: =_xlfn.IFNA(VLOOKUP($A7,公司与JV对应关系!$A:$D,4,0),"")
A8: 00006 | B8: China Guide Resources Limited | C8: 中诚资源有限公司 | F8: =_xlfn.IFNA(IF(MATCH(A8,'JV and CTP清单'!A:A,0)>0,"是",""),"否") -> 是 | G8: =_xlfn.IFNA(VLOOKUP($A8,公司与JV对应关系!$A:$D,3,0),"") | H8: =_xlfn.IFNA(VLOOKUP($A8,公司与JV对应关系!$A:$D,4,0),"")
A9: 00007 | B9: Smoothing Investment Limited | C9: 伟诚倡投资有限公司 | F9: =_xlfn.IFNA(IF(MATCH(A9,'JV and CTP清单'!A:A,0)>0,"是",""),"否") -> 是 | G9: =_xlfn.IFNA(VLOOKUP($A9,公司与JV对应关系!$A:$D,3,0),"") | H9: =_xlfn.IFNA(VLOOKUP($A9,公司与JV对应关系!$A:$D,4,0),"")
A10: 00008 | B10: Quality Testing Services Limited | C10: 质量测检服务有限公司 | F10: =_xlfn.IFNA(IF(MATCH(A10,'JV and CTP清单'!A:A,0)>0,"是",""),"否") -> 是 | G10: =_xlfn.IFNA(VLOOKUP($A10,公司与JV对应关系!$A:$D,3,0),"") | H10: =_xlfn.IFNA(VLOOKUP($A10,公司与JV对应关系!$A:$D,4,0),"")
A11: 00009 | B11: P-Tech Engineering Company Limited | C11: 卓诚工程有限公司 | F11: =_xlfn.IFNA(IF(MATCH(A11,'JV and CTP清单'!A:A,0)>0,"是",""),"否") -> 是 | G11: =_xlfn.IFNA(VLOOKUP($A11,公司与JV对应关系!$A:$D,3,0),"") | H11: =_xlfn.IFNA(VLOOKUP($A11,公司与JV对应关系!$A:$D,4,0),"")
A12: 00010 | B12: China Gas Company Limited | C12: 中华煤气有限公司 | F12: =_xlfn.IFNA(IF(MATCH(A12,'JV and CTP清单'!A:A,0)>0,"是",""),"否") -> 是 | G12: =_xlfn.IFNA(VLOOKUP($A12,公司与JV对应关系!$A:$D,3,0),"") | H12: =_xlfn.IFNA(VLOOKUP($A12,公司与JV对应关系!$A:$D,4,0),"")
A13: 00011 | B13: Hong Kong Gas Company Limited | C13: 香港煤气有限公司 | F13: =_xlfn.IFNA(IF(MATCH(A13,'JV and CTP清单'!A:A,0)>0,"是",""),"否") -> 是 | G13: =_xlfn.IFNA(VLOOKUP($A13,公司与JV对应关系!$A:$D,3,0),"") | H13: =_xlfn.IFNA(VLOOKUP($A13,公司与JV对应关系!$A:$D,4,0),"")
A14: 00012 | B14: Alpha Idea International Limited | C14: 星满国际有限公司 | F14: =_xlfn.IFNA(IF(MATCH(A14,'JV and CTP清单'!A:A,0)>0,"是",""),"否") -> 是 | G14: =_xlfn.IFNA(VLOOKUP($A14,公司与JV对应关系!$A:$D,3,0),"") | H14: =_xlfn.IFNA(VLOOKUP($A14,公司与JV对应关系!$A:$D,4,0),"")
... A779: 00777 | B779: 宁波盛凯能源科技有限公司 | C779: 宁波盛凯能源科技有限公司 | F779: =_xlfn.IFNA(IF(MATCH(A779,'JV and CTP清单'!A:A,0)>0,"是",""),"否") -> 是 | G779: =_xlfn.IFNA(VLOOKUP($A779,公司与JV对应关系!$A:$D,3,0),"") | H779: =_xlfn.IFNA(VLOOKUP($A779,公司与JV对应关系!$A:$D,4,0),"")
A780: 00778 | B780: 宣城坤能新能源科技有限公司（重复，停用） | C780: 宣城坤能新能源科技有限公司（重复，停用） | E780: 44926 | F780: =_xlfn.IFNA(IF(MATCH(A780,'JV and CTP清单'!A:A,0)>0,"是",""),"否") -> 是 | G780: =_xlfn.IFNA(VLOOKUP($A780,公司与JV对应关系!$A:$D,3,0),"") | H780: =_xlfn.IFNA(VLOOKUP($A780,公司与JV对应关系!$A:$D,4,0),"")
A781: 00779 | B781: 徐州普未光合能源科技有限公司 | C781: 徐州普未光合能源科技有限公司 | F781: =_xlfn.IFNA(IF(MATCH(A781,'JV and CTP清单'!A:A,0)>0,"是",""),"否") -> 是 | G781: =_xlfn.IFNA(VLOOKUP($A781,公司与JV对应关系!$A:$D,3,0),"") | H781: =_xlfn.IFNA(VLOOKUP($A781,公司与JV对应关系!$A:$D,4,0),"")
A782: 00780 | B782: 上海兆熙新能源科技有限公司 | C782: 上海兆熙新能源科技有限公司 | F782: =_xlfn.IFNA(IF(MATCH(A782,'JV and CTP清单'!A:A,0)>0,"是",""),"否") -> 是 | G782: =_xlfn.IFNA(VLOOKUP($A782,公司与JV对应关系!$A:$D,3,0),"") | H782: =_xlfn.IFNA(VLOOKUP($A782,公司与JV对应关系!$A:$D,4,0),"")
A783: 00781 | B783: 温州狮耀新能源有限公司 | C783: 温州狮耀新能源有限公司 | F783: =_xlfn.IFNA(IF(MATCH(A783,'JV and CTP清单'!A:A,0)>0,"是",""),"否") -> 是 | G783: =_xlfn.IFNA(VLOOKUP($A783,公司与JV对应关系!$A:$D,3,0),"") | H783: =_xlfn.IFNA(VLOOKUP($A783,公司与JV对应关系!$A:$D,4,0),"")
A784: 00782 | B784: 丹阳市晶能光伏电力有限公司 | C784: 丹阳市晶能光伏电力有限公司 | F784: =_xlfn.IFNA(IF(MATCH(A784,'JV and CTP清单'!A:A,0)>0,"是",""),"否") -> 是 | G784: =_xlfn.IFNA(VLOOKUP($A784,公司与JV对应关系!$A:$D,3,0),"") | H784: =_xlfn.IFNA(VLOOKUP($A784,公司与JV对应关系!$A:$D,4,0),"")
A785: 00783 | B785: 镇江市中盛清洁能源有限公司 | C785: 镇江市中盛清洁能源有限公司 | F785: =_xlfn.IFNA(IF(MATCH(A785,'JV and CTP清单'!A:A,0)>0,"是",""),"否") -> 是 | G785: =_xlfn.IFNA(VLOOKUP($A785,公司与JV对应关系!$A:$D,3,0),"") | H785: =_xlfn.IFNA(VLOOKUP($A785,公司与JV对应关系!$A:$D,4,0),"")
A786: 00784 | B786: 睢宁县晶能光伏电力有限公司 | C786: 睢宁县晶能光伏电力有限公司 | F786: =_xlfn.IFNA(IF(MATCH(A786,'JV and CTP清单'!A:A,0)>0,"是",""),"否") -> 是 | G786: =_xlfn.IFNA(VLOOKUP($A786,公司与JV对应关系!$A:$D,3,0),"") | H786: =_xlfn.IFNA(VLOOKUP($A786,公司与JV对应关系!$A:$D,4,0),"")
A787: 00785 | B787: 常州科鸿光伏电力有限公司 | C787: 常州科鸿光伏电力有限公司 | F787: =_xlfn.IFNA(IF(MATCH(A787,'JV and CTP清单'!A:A,0)>0,"是",""),"否") -> 是 | G787: =_xlfn.IFNA(VLOOKUP($A787,公司与JV对应关系!$A:$D,3,0),"") | H787: =_xlfn.IFNA(VLOOKUP($A787,公司与JV对应关系!$A:$D,4,0),"")
A788: 00786 | B788: 凤阳纤安新能源有限公司 | C788: 凤阳纤安新能源有限公司 | F788: =_xlfn.IFNA(IF(MATCH(A788,'JV and CTP清单'!A:A,0)>0,"是",""),"否") -> 是 | G788: =_xlfn.IFNA(VLOOKUP($A788,公司与JV对应关系!$A:$D,3,0),"") | H788: =_xlfn.IFNA(VLOOKUP($A788,公司与JV对应关系!$A:$D,4,0),"")
A789: 00787 | B789: 武汉国楚云天新能源有限公司 | C789: 武汉国楚云天新能源有限公司 | F789: =_xlfn.IFNA(IF(MATCH(A789,'JV and CTP清单'!A:A,0)>0,"是",""),"否") -> 是 | G789: =_xlfn.IFNA(VLOOKUP($A789,公司与JV对应关系!$A:$D,3,0),"") | H789: =_xlfn.IFNA(VLOOKUP($A789,公司与JV对应关系!$A:$D,4,0),"")
A790: 00788 | B790: 宿州百嘉光伏科技有限公司 | C790: 宿州百嘉光伏科技有限公司 | F790: =_xlfn.IFNA(IF(MATCH(A790,'JV and CTP清单'!A:A,0)>0,"是",""),"否") -> 是 | G790: =_xlfn.IFNA(VLOOKUP($A790,公司与JV对应关系!$A:$D,3,0),"") | H790: =_xlfn.IFNA(VLOOKUP($A790,公司与JV对应关系!$A:$D,4,0),"")
A791: 00789 | B791: 宁波森康能源科技有限公司 | C791: 宁波森康能源科技有限公司 | F791: =_xlfn.IFNA(IF(MATCH(A791,'JV and CTP清单'!A:A,0)>0,"是",""),"否") -> 否 | G791: =_xlfn.IFNA(VLOOKUP($A791,公司与JV对应关系!$A:$D,3,0),"") -> 00765 | H791: =_xlfn.IFNA(VLOOKUP($A791,公司与JV对应关系!$A:$D,4,0),"") -> 宁波联阔新能源有限公司
A792: 00790 | B792: 余姚南泰光伏发电有限公司 | C792: 余姚南泰光伏发电有限公司 | F792: =_xlfn.IFNA(IF(MATCH(A792,'JV and CTP清单'!A:A,0)>0,"是",""),"否") -> 否 | G792: =_xlfn.IFNA(VLOOKUP($A792,公司与JV对应关系!$A:$D,3,0),"") -> 00765 | H792: =_xlfn.IFNA(VLOOKUP($A792,公司与JV对应关系!$A:$D,4,0),"") -> 宁波联阔新能源有限公司
... A1827: 01825 | B1827: 西安秦华天然气有限公司 | C1827: 西安秦华天然气有限公司 | F1827: =_xlfn.IFNA(IF(MATCH(A1827,'JV and CTP清单'!A:A,0)>0,"是",""),"否") -> 否 | G1827: =_xlfn.IFNA(VLOOKUP($A1827,公司与JV对应关系!$A:$D,3,0),"") | H1827: =_xlfn.IFNA(VLOOKUP($A1827,公司与JV对应关系!$A:$D,4,0),"")
A1828: 01826 | B1828: 大连德泰港能投智慧能源有限公司（重复，停用） | C1828: 大连德泰港能投智慧能源有限公司（重复，停用） | E1828: 44926 | F1828: =_xlfn.IFNA(IF(MATCH(A1828,'JV and CTP清单'!A:A,0)>0,"是",""),"否") -> 是 | G1828: =_xlfn.IFNA(VLOOKUP($A1828,公司与JV对应关系!$A:$D,3,0),"") | H1828: =_xlfn.IFNA(VLOOKUP($A1828,公司与JV对应关系!$A:$D,4,0),"")
A1829: 01827 | B1829: 佛山市燃气集团股份有限公司 | C1829: 佛山市燃气集团股份有限公司 | F1829: =_xlfn.IFNA(IF(MATCH(A1829,'JV and CTP清单'!A:A,0)>0,"是",""),"否") -> 是 | G1829: =_xlfn.IFNA(VLOOKUP($A1829,公司与JV对应关系!$A:$D,3,0),"") | H1829: =_xlfn.IFNA(VLOOKUP($A1829,公司与JV对应关系!$A:$D,4,0),"")
A1830: 01828 | B1830: 潮州枫溪深能港华燃气有限公司 | C1830: 潮州枫溪深能港华燃气有限公司 | F1830: =_xlfn.IFNA(IF(MATCH(A1830,'JV and CTP清单'!A:A,0)>0,"是",""),"否") -> 是 | G1830: =_xlfn.IFNA(VLOOKUP($A1830,公司与JV对应关系!$A:$D,3,0),"") -> 01183 | H1830: =_xlfn.IFNA(VLOOKUP($A1830,公司与JV对应关系!$A:$D,4,0),"") -> 潮州深能港华燃气有限公司
A1831: 01829 | B1831: 武汉市车都天然气有限公司 | C1831: 武汉市车都天然气有限公司 | F1831: =_xlfn.IFNA(IF(MATCH(A1831,'JV and CTP清单'!A:A,0)>0,"是",""),"否") -> 是 | G1831: =_xlfn.IFNA(VLOOKUP($A1831,公司与JV对应关系!$A:$D,3,0),"") | H1831: =_xlfn.IFNA(VLOOKUP($A1831,公司与JV对应关系!$A:$D,4,0),"")
A1832: 01830 | B1832: 石家庄建投天然气有限公司 | C1832: 石家庄建投天然气有限公司 | F1832: =_xlfn.IFNA(IF(MATCH(A1832,'JV and CTP清单'!A:A,0)>0,"是",""),"否") -> 是 | G1832: =_xlfn.IFNA(VLOOKUP($A1832,公司与JV对应关系!$A:$D,3,0),"") | H1832: =_xlfn.IFNA(VLOOKUP($A1832,公司与JV对应关系!$A:$D,4,0),"")
A1833: 01831 | B1833: 承德市建投天然气有限责任公司 | C1833: 承德市建投天然气有限责任公司 | F1833: =_xlfn.IFNA(IF(MATCH(A1833,'JV and CTP清单'!A:A,0)>0,"是",""),"否") -> 是 | G1833: =_xlfn.IFNA(VLOOKUP($A1833,公司与JV对应关系!$A:$D,3,0),"") -> 00286 | H1833: =_xlfn.IFNA(VLOOKUP($A1833,公司与JV对应关系!$A:$D,4,0),"") -> Hebei Natural Gas Company Limited
A1834: 01832 | B1834: 清河县建投天然气有限公司 | C1834: 清河县建投天然气有限公司 | F1834: =_xlfn.IFNA(IF(MATCH(A1834,'JV and CTP清单'!A:A,0)>0,"是",""),"否") -> 是 | G1834: =_xlfn.IFNA(VLOOKUP($A1834,公司与JV对应关系!$A:$D,3,0),"") -> 00286 | H1834: =_xlfn.IFNA(VLOOKUP($A1834,公司与JV对应关系!$A:$D,4,0),"") -> Hebei Natural Gas Company Limited
A1835: 01833 | B1835: 晋州市建投燃气有限公司 | C1835: 晋州市建投燃气有限公司 | F1835: =_xlfn.IFNA(IF(MATCH(A1835,'JV and CTP清单'!A:A,0)>0,"是",""),"否") -> 是 | G1835: =_xlfn.IFNA(VLOOKUP($A1835,公司与JV对应关系!$A:$D,3,0),"") -> 00286 | H1835: =_xlfn.IFNA(VLOOKUP($A1835,公司与JV对应关系!$A:$D,4,0),"") -> Hebei Natural Gas Company Limited
A1836: 01834 | B1836: 深州市建投燃气有限公司 | C1836: 深州市建投燃气有限公司 | F1836: =_xlfn.IFNA(IF(MATCH(A1836,'JV and CTP清单'!A:A,0)>0,"是",""),"否") -> 是 | G1836: =_xlfn.IFNA(VLOOKUP($A1836,公司与JV对应关系!$A:$D,3,0),"") -> 00286 | H1836: =_xlfn.IFNA(VLOOKUP($A1836,公司与JV对应关系!$A:$D,4,0),"") -> Hebei Natural Gas Company Limited
A1837: 01835 | B1837: 宁晋县建投天然气有限责任公司 | C1837: 宁晋县建投天然气有限责任公司 | F1837: =_xlfn.IFNA(IF(MATCH(A1837,'JV and CTP清单'!A:A,0)>0,"是",""),"否") -> 是 | G1837: =_xlfn.IFNA(VLOOKUP($A1837,公司与JV对应关系!$A:$D,3,0),"") | H1837: =_xlfn.IFNA(VLOOKUP($A1837,公司与JV对应关系!$A:$D,4,0),"")
A1838: 01836 | B1838: 临西县新能天然气工程有限公司 | C1838: 临西县新能天然气工程有限公司 | F1838: =_xlfn.IFNA(IF(MATCH(A1838,'JV and CTP清单'!A:A,0)>0,"是",""),"否") -> 否 | G1838: =_xlfn.IFNA(VLOOKUP($A1838,公司与JV对应关系!$A:$D,3,0),"") | H1838: =_xlfn.IFNA(VLOOKUP($A1838,公司与JV对应关系!$A:$D,4,0),"")
A1839: 01837 | B1839: 衡水建投天然气有限公司 | C1839: 衡水建投天然气有限公司 | F1839: =_xlfn.IFNA(IF(MATCH(A1839,'JV and CTP清单'!A:A,0)>0,"是",""),"否") -> 否 | G1839: =_xlfn.IFNA(VLOOKUP($A1839,公司与JV对应关系!$A:$D,3,0),"") | H1839: =_xlfn.IFNA(VLOOKUP($A1839,公司与JV对应关系!$A:$D,4,0),"")
A1840: 01838 | B1840: 辛集市建投燃气有限公司 | C1840: 辛集市建投燃气有限公司 | F1840: =_xlfn.IFNA(IF(MATCH(A1840,'JV and CTP清单'!A:A,0)>0,"是",""),"否") -> 是 | G1840: =_xlfn.IFNA(VLOOKUP($A1840,公司与JV对应关系!$A:$D,3,0),"") -> 00286 | H1840: =_xlfn.IFNA(VLOOKUP($A1840,公司与JV对应关系!$A:$D,4,0),"") -> Hebei Natural Gas Company Limited
... A2302: 02427 | B2302: 常州泽溪能源科技有限公司 | C2302: 常州泽溪能源科技有限公司 | F2302: =_xlfn.IFNA(IF(MATCH(A2302,'JV and CTP清单'!A:A,0)>0,"是",""),"否") -> 否 | G2302: =_xlfn.IFNA(VLOOKUP($A2302,公司与JV对应关系!$A:$D,3,0),"") | H2302: =_xlfn.IFNA(VLOOKUP($A2302,公司与JV对应关系!$A:$D,4,0),"")

Sheet 公司与JV对应关系
A1: Company (Subsidiary) | C1: Entity (JV) | E1: Start Period | F1: End Period
A2: 00455 | B2: Lane Success Development Limited | C2: 00044 | D2: Monarch Properties Limited
A3: 00134 | B3: ECO Orient Energy (Thailand) Ltd. | C3: 00135 | D3: ECO Orient Resources (Thailand) Ltd.
A4: 00462 | B4: EcoCeres, Inc. | C4: 00195 | D4: EcoCeres, Inc.
A5: 00465 | B5: Everwealth Investment Management, Inc. | C5: 00195 | D5: EcoCeres, Inc.
A6: 00466 | B6: ECO Bio-Grease Utilization Company Limited | C6: 00195 | D6: EcoCeres, Inc.
A7: 00467 | B7: ECO Agricultural Resources Utilization Company Limited | C7: 00195 | D7: EcoCeres, Inc.
A8: 00468 | B8: ECO Trading Investments Limited | C8: 00195 | D8: EcoCeres, Inc.
A9: 00469 | B9: ECO Energy Resources Limited | C9: 00195 | D9: EcoCeres, Inc.
A10: 00470 | B10: ECO Bio-Grease (Zhangjiagang) Investments Company Limited | C10: 00195 | D10: EcoCeres, Inc.
A11: 00471 | B11: ECO Green Hydrogen Investments Company Limited | C11: 00195 | D11: EcoCeres, Inc.
A12: 00472 | B12: ECO Biotechnology Investments Company Limited | C12: 00195 | D12: EcoCeres, Inc.
A13: 00473 | B13: ECO Biofuel Technology Investments Company Limited | C13: 00195 | D13: EcoCeres, Inc.
... A796: 02261 | B796: 深汭（上海）综合能源服务有限公司 | C796: 02278 | D796: 深圳港华慧能科技有限公司

Sheet 各板块数据
A1: 板块 | B1: 单位名称 | C1: TA匹配 | D1: MT
A2: MU | B2: 国家管网集团吉林天然气管道有限责任公司 | C2: =VLOOKUP(B2,公司清单!C:C,1,FALSE) -> #N/A | D2: =VLOOKUP(B2,'JV and CTP清单'!C:C,1,FALSE) -> #N/A
A3: MU | B3: 吉林港华清洁能源有限公司 | C3: =VLOOKUP(B3,公司清单!C:C,1,FALSE) -> 吉林港华清洁能源有限公司 | D3: =VLOOKUP(B3,'JV and CTP清单'!C:C,1,FALSE) -> #N/A
A4: MU | B4: 石家庄建投天然气有限公司 | C4: =VLOOKUP(B4,公司清单!C:C,1,FALSE) -> 石家庄建投天然气有限公司 | D4: =VLOOKUP(B4,'JV and CTP清单'!C:C,1,FALSE) -> #N/A
A5: MU | B5: 河北赵都天然气有限责任公司 | C5: =VLOOKUP(B5,公司清单!C:C,1,FALSE) -> 河北赵都天然气有限责任公司 | D5: =VLOOKUP(B5,'JV and CTP清单'!C:C,1,FALSE) -> #N/A
A6: MU | B6: 承德市建投天然气有限责任公司 | C6: =VLOOKUP(B6,公司清单!C:C,1,FALSE) -> 承德市建投天然气有限责任公司 | D6: =VLOOKUP(B6,'JV and CTP清单'!C:C,1,FALSE) -> #N/A
A7: MU | B7: 宁晋县建投天然气有限责任公司 | C7: =VLOOKUP(B7,公司清单!C:C,1,FALSE) -> 宁晋县建投天然气有限责任公司 | D7: =VLOOKUP(B7,'JV and CTP清单'!C:C,1,FALSE) -> #N/A
A8: MU | B8: 深州市建投燃气有限公司 | C8: =VLOOKUP(B8,公司清单!C:C,1,FALSE) -> 深州市建投燃气有限公司 | D8: =VLOOKUP(B8,'JV and CTP清单'!C:C,1,FALSE) -> #N/A
A9: MU | B9: 辛集市建投燃气有限公司 | C9: =VLOOKUP(B9,公司清单!C:C,1,FALSE) -> 辛集市建投燃气有限公司 | D9: =VLOOKUP(B9,'JV and CTP清单'!C:C,1,FALSE) -> #N/A
A10: MU | B10: 晋州市建投燃气有限公司 | C10: =VLOOKUP(B10,公司清单!C:C,1,FALSE) -> 晋州市建投燃气有限公司 | D10: =VLOOKUP(B10,'JV and CTP清单'!C:C,1,FALSE) -> #N/A
A11: MU | B11: 中石油京唐液化天然气有限公司 | C11: =VLOOKUP(B11,公司清单!C:C,1,FALSE) -> 中石油京唐液化天然气有限公司 | D11: =VLOOKUP(B11,'JV and CTP清单'!C:C,1,FALSE) -> #N/A
A12: MU | B12: 石家庄冀燃管道工程有限公司 | C12: =VLOOKUP(B12,公司清单!C:C,1,FALSE) -> 石家庄冀燃管道工程有限公司 | D12: =VLOOKUP(B12,'JV and CTP清单'!C:C,1,FALSE) -> #N/A
A13: MU | B13: 邢台冀燃天然气有限公司 | C13: =VLOOKUP(B13,公司清单!C:C,1,FALSE) -> 邢台冀燃天然气有限公司 | D13: =VLOOKUP(B13,'JV and CTP清单'!C:C,1,FALSE) -> #N/A
... A1342: 绿燃 | B1342: 臻新绿源科技(佛山)有限公司 | C1342: =VLOOKUP(B1342,公司清单!C:C,1,FALSE) -> #N/A | D1342: =VLOOKUP(B1342,'JV and CTP清单'!C:C,1,FALSE) -> #N/A

Sheet 对比
B1: 板块 | C1: 数量
B2: 内地公用 | C2: 575
B3: 再生能源 | C3: =11+206+4+419 -> 640
B4: 延伸 | C4: 98
B5: 气源 | C5: 26
B6: 绿燃 | C6: 2
B7: 合计 | C7: =SUM(C2:C6) -> 1341
B8: 来源：各板块提交清单
B10: 与JV对比情况：
B11: 一级JV总数 | C11: 未匹配总数 | D11: 易高 | E11: 中华煤气BVI | F11: 英文 | G11: 未匹配
B12: 850 | C12: 428 | D12: 95 | E12: 95 | F12: 65 | G12: =C12-D12-E12-F12 -> 173
G13: BVI | H13: 24
G14: HK | H14: 77
G15: 其他（72家） | H15: =72-I15 -> 58 | I15: 14

Sheet 72家未匹配
A1: 名称 | B1: Frango Code | C1: Node - Description
A2: 港華能源研究院控股有限公司 | B2: =VLOOKUP(A2,'JV and CTP清单'!C:P,5,FALSE) -> #N/A | C2: =VLOOKUP(A2,'JV and CTP清单'!C:P,13,FALSE) -> #N/A
A3: 安丘航洲新能源科技有限公司 | B3: =VLOOKUP(A3,'JV and CTP清单'!C:P,5,FALSE) -> PGAQJV | C3: =VLOOKUP(A3,'JV and CTP清单'!C:P,13,FALSE) -> Shandong
A4: 巴彦淖尔市耀进燃气有限公司 | B4: =VLOOKUP(A4,'JV and CTP清单'!C:P,5,FALSE) -> BYYJJV | C4: =VLOOKUP(A4,'JV and CTP清单'!C:P,13,FALSE) -> Inner Mongoria
A5: 保源環境投資有限公司 | B5: =VLOOKUP(A5,'JV and CTP清单'!C:P,5,FALSE) -> 0 | C5: =VLOOKUP(A5,'JV and CTP清单'!C:P,13,FALSE) -> Hong Kong
A6: 北京驰波名气通数据服务有限公司 | B6: =VLOOKUP(A6,'JV and CTP清单'!C:P,5,FALSE) -> TBCTJV | C6: =VLOOKUP(A6,'JV and CTP清单'!C:P,13,FALSE) -> Beijing
A7: 亳州皖华燃气有限公司 | B7: =VLOOKUP(A7,'JV and CTP清单'!C:P,5,FALSE) -> N/A | C7: =VLOOKUP(A7,'JV and CTP清单'!C:P,13,FALSE) -> Anhui
A8: 常州道胜科技产业有限公司 | B8: =VLOOKUP(A8,'JV and CTP清单'!C:P,5,FALSE) -> EICDJV | C8: =VLOOKUP(A8,'JV and CTP清单'!C:P,13,FALSE) -> #N/A
A9: 潮盛投资有限公司 | B9: =VLOOKUP(A9,'JV and CTP清单'!C:P,5,FALSE) -> CSIL | C9: =VLOOKUP(A9,'JV and CTP清单'!C:P,13,FALSE) -> Hong Kong
A10: 潮州枫溪港华燃气有限公司 | B10: =VLOOKUP(A10,'JV and CTP清单'!C:P,5,FALSE) -> GDFX | C10: =VLOOKUP(A10,'JV and CTP清单'!C:P,13,FALSE) -> Guangdong
A11: 潮州港华燃气有限公司 | B11: =VLOOKUP(A11,'JV and CTP清单'!C:P,5,FALSE) -> CUJV | C11: =VLOOKUP(A11,'JV and CTP清单'!C:P,13,FALSE) -> Guangdong
A12: 滁州港华综合能源有限公司（合并） | B12: =VLOOKUP(A12,'JV and CTP清单'!C:P,5,FALSE) -> 0 | C12: =VLOOKUP(A12,'JV and CTP清单'!C:P,13,FALSE) -> Anhui | D12: 滁州港华综合能源有限公司
A13: 创熙投资有限公司 | B13: =VLOOKUP(A13,'JV and CTP清单'!C:P,5,FALSE) -> EXCI | C13: =VLOOKUP(A13,'JV and CTP清单'!C:P,13,FALSE) -> BVI
A14: 大连德泰港能投智慧能源有限公司 (Disable) | B14: =VLOOKUP(A14,'JV and CTP清单'!C:P,5,FALSE) -> SEDLJV | C14: =VLOOKUP(A14,'JV and CTP清单'!C:P,13,FALSE) -> Liaoning | D14: 大连德泰港能投智慧能源有限公司
A15: 大连名气通数据服务有限公司 | B15: =VLOOKUP(A15,'JV and CTP清单'!C:P,5,FALSE) -> TTDCJV | C15: =VLOOKUP(A15,'JV and CTP清单'!C:P,13,FALSE) -> Liaoning
A16: 大连屹化新能源科技发展有限公司 | B16: =VLOOKUP(A16,'JV and CTP清单'!C:P,5,FALSE) -> DLTDJV | C16: =VLOOKUP(A16,'JV and CTP清单'!C:P,13,FALSE) -> Liaoning
A17: 丹阳卓惠洗涤有限公司 | B17: =VLOOKUP(A17,'JV and CTP清单'!C:P,5,FALSE) -> CTECDY | C17: =VLOOKUP(A17,'JV and CTP清单'!C:P,13,FALSE) -> #N/A
A18: 得志发展有限公司 | B18: =VLOOKUP(A18,'JV and CTP清单'!C:P,5,FALSE) -> SRDL | C18: =VLOOKUP(A18,'JV and CTP清单'!C:P,13,FALSE) -> Hong Kong
A19: 东莞名气通数据服务有限公司 | B19: =VLOOKUP(A19,'JV and CTP清单'!C:P,5,FALSE) -> TTDGJV | C19: =VLOOKUP(A19,'JV and CTP清单'!C:P,13,FALSE) -> Guangdong
A20: 恩发投资有限公司 | B20: =VLOOKUP(A20,'JV and CTP清单'!C:P,5,FALSE) -> FANI | C20: =VLOOKUP(A20,'JV and CTP清单'!C:P,13,FALSE) -> Hong Kong
A21: 丰城新高焦化有限公司 | B21: =VLOOKUP(A21,'JV and CTP清单'!C:P,5,FALSE) -> FCXCJV | C21: =VLOOKUP(A21,'JV and CTP清单'!C:P,13,FALSE) -> Jiangxi
A22: 港华国际贸易 | B22: =VLOOKUP(A22,'JV and CTP清单'!C:P,5,FALSE) -> NYMY | C22: =VLOOKUP(A22,'JV and CTP清单'!C:P,13,FALSE) -> Mainland China
A23: 港华技术服务（深圳）有限公司 | B23: =VLOOKUP(A23,'JV and CTP清单'!C:P,5,FALSE) -> HPTSZ | C23: =VLOOKUP(A23,'JV and CTP清单'!C:P,13,FALSE) -> Guangdong
A24: 港华能源研究院有限公司 | B24: =VLOOKUP(A24,'JV and CTP清单'!C:P,5,FALSE) -> TGEA | C24: =VLOOKUP(A24,'JV and CTP清单'!C:P,13,FALSE) -> Hong Kong
A25: 港华燃气（枫溪）有限公司 | B25: =VLOOKUP(A25,'JV and CTP清单'!C:P,5,FALSE) -> TCFX | C25: =VLOOKUP(A25,'JV and CTP清单'!C:P,13,FALSE) -> Hong Kong
A26: 港华燃气（融资）有限公司 | B26: =VLOOKUP(A26,'JV and CTP清单'!C:P,5,FALSE) -> TCFL | C26: =VLOOKUP(A26,'JV and CTP清单'!C:P,13,FALSE) -> Hong Kong
... A35: 港华燃气企业有限公司 | B35: =VLOOKUP(A35,'JV and CTP清单'!C:P,5,FALSE) -> N/A | C35: =VLOOKUP(A35,'JV and CTP清单'!C:P,13,FALSE) -> BVI
A36: 港华舒适家（成都）科技服务有限公司 | B36: =VLOOKUP(A36,'JV and CTP清单'!C:P,5,FALSE) -> TCHCD | C36: =VLOOKUP(A36,'JV and CTP清单'!C:P,13,FALSE) -> Sichuan | D36: 港华舒适家成都新都科技服务有限公司
A37: 港华智慧能源（燃气）控股有限公司 | B37: =VLOOKUP(A37,'JV and CTP清单'!C:P,5,FALSE) -> TSHL | C37: =VLOOKUP(A37,'JV and CTP清单'!C:P,13,FALSE) -> Hong Kong
A38: 港华智慧能源（燃气）投资有限公司 | B38: =VLOOKUP(A38,'JV and CTP清单'!C:P,5,FALSE) -> TSIL | C38: =VLOOKUP(A38,'JV and CTP清单'!C:P,13,FALSE) -> Hong Kong
A39: 港华智慧能源有限公司 | B39: =VLOOKUP(A39,'JV and CTP清单'!C:P,5,FALSE) -> TOWN | C39: =VLOOKUP(A39,'JV and CTP清单'!C:P,13,FALSE) -> Cayman Islands
A40: 港华中国电力（香港）综合智慧能源有限公司 | B40: =VLOOKUP(A40,'JV and CTP清单'!C:P,5,FALSE) -> TPIE | C40: =VLOOKUP(A40,'JV and CTP清单'!C:P,13,FALSE) -> Hong Kong
A41: 港华卓明信息（深圳）有限公司 | B41: =VLOOKUP(A41,'JV and CTP清单'!C:P,5,FALSE) -> HFSSZ | C41: =VLOOKUP(A41,'JV and CTP清单'!C:P,13,FALSE) -> Guangdong
A42: 港華紫荊農莊(句容)有限公司 | B42: =VLOOKUP(A42,'JV and CTP清单'!C:P,5,FALSE) -> 0 | C42: =VLOOKUP(A42,'JV and CTP清单'!C:P,13,FALSE) -> Mainland China
A43: 港投分布式能源（融资）有限公司 | B43: =VLOOKUP(A43,'JV and CTP清单'!C:P,5,FALSE) -> HEFL | C43: =VLOOKUP(A43,'JV and CTP清单'!C:P,13,FALSE) -> Hong Kong
A44: 港投分布式能源控股有限公司 | B44: =VLOOKUP(A44,'JV and CTP清单'!C:P,5,FALSE) -> HEHC | C44: =VLOOKUP(A44,'JV and CTP清单'!C:P,13,FALSE) -> Hong Kong
A45: 港投分布式能源投资控股有限公司 | B45: =VLOOKUP(A45,'JV and CTP清单'!C:P,5,FALSE) -> HEIH | C45: =VLOOKUP(A45,'JV and CTP清单'!C:P,13,FALSE) -> BVI
A46: 港投综合电能（融资）有限公司 | B46: =VLOOKUP(A46,'JV and CTP清单'!C:P,5,FALSE) -> HPFL | C46: =VLOOKUP(A46,'JV and CTP清单'!C:P,13,FALSE) -> Hong Kong
A47: 港投综合电能控股有限公司 | B47: =VLOOKUP(A47,'JV and CTP清单'!C:P,5,FALSE) -> HPHC | C47: =VLOOKUP(A47,'JV and CTP清单'!C:P,13,FALSE) -> Hong Kong
A48: 港投综合电能投资控股有限公司 | B48: =VLOOKUP(A48,'JV and CTP清单'!C:P,5,FALSE) -> HPIH | C48: =VLOOKUP(A48,'JV and CTP清单'!C:P,13,FALSE) -> BVI
... A69: 江西丰龙矿业有限责任公司 | B69: =VLOOKUP(A69,'JV and CTP清单'!C:P,5,FALSE) -> JXFLJV | C69: =VLOOKUP(A69,'JV and CTP清单'!C:P,13,FALSE) -> Jiangxi
A70: 江阴港能投智慧能源有限公司（合并） | B70: =VLOOKUP(A70,'JV and CTP清单'!C:P,5,FALSE) -> GDJYPE | C70: =VLOOKUP(A70,'JV and CTP清单'!C:P,13,FALSE) -> Guangdong | D70: 揭阳港能投智慧能源有限公司
A71: 江阴港能投智慧能源有限公司（合并） | B71: =VLOOKUP(A71,'JV and CTP清单'!C:P,5,FALSE) -> GDJYPE | C71: =VLOOKUP(A71,'JV and CTP清单'!C:P,13,FALSE) -> Guangdong | D71: 江阴港能投智慧能源有限公司
A72: 江阴港能投智慧能源有限公司（合并） | B72: =VLOOKUP(A72,'JV and CTP清单'!C:P,5,FALSE) -> GDJYPE | C72: =VLOOKUP(A72,'JV and CTP清单'!C:P,13,FALSE) -> Guangdong | D72: 宁夏环能新能源有限公司
A73: 精裕国际有限公司 | B73: =VLOOKUP(A73,'JV and CTP清单'!C:P,5,FALSE) -> ELIL | C73: =VLOOKUP(A73,'JV and CTP清单'!C:P,13,FALSE) -> Hong Kong
A74: 景德镇投资有限公司 | B74: =VLOOKUP(A74,'JV and CTP清单'!C:P,5,FALSE) -> JDZI | C74: =VLOOKUP(A74,'JV and CTP清单'!C:P,13,FALSE) -> BVI
A75: 罗平县龙驰煤业有限责任公司 | B75: =VLOOKUP(A75,'JV and CTP清单'!C:P,5,FALSE) -> LPLCJV | C75: =VLOOKUP(A75,'JV and CTP清单'!C:P,13,FALSE) -> Yunnan
A76: 绿智碳认证国际顾问服务有限公司 | B76: =VLOOKUP(A76,'JV and CTP清单'!C:P,5,FALSE) -> CTFL | C76: =VLOOKUP(A76,'JV and CTP清单'!C:P,13,FALSE) -> Hong Kong
A77: 煤气企业有限公司 | B77: =VLOOKUP(A77,'JV and CTP清单'!C:P,5,FALSE) -> TREL | C77: =VLOOKUP(A77,'JV and CTP清单'!C:P,13,FALSE) -> Hong Kong
A78: 煤气投资有限公司 | B78: =VLOOKUP(A78,'JV and CTP清单'!C:P,5,FALSE) -> TGIN | C78: =VLOOKUP(A78,'JV and CTP清单'!C:P,13,FALSE) -> Hong Kong
A79: 名气家（香港）有限公司 | B79: =VLOOKUP(A79,'JV and CTP清单'!C:P,5,FALSE) -> TGHK | C79: =VLOOKUP(A79,'JV and CTP清单'!C:P,13,FALSE) -> Hong Kong
A80: 名气家（中国）有限公司 | B80: =VLOOKUP(A80,'JV and CTP清单'!C:P,5,FALSE) -> TGLS | C80: =VLOOKUP(A80,'JV and CTP清单'!C:P,13,FALSE) -> Hong Kong
A81: 名气家控股有限公司 (CAY) | B81: =VLOOKUP(A81,'JV and CTP清单'!C:P,5,FALSE) -> TGLH | C81: =VLOOKUP(A81,'JV and CTP清单'!C:P,13,FALSE) -> Cayman Islands
A82: 名气家控股有限公司 (HK) | B82: =VLOOKUP(A82,'JV and CTP清单'!C:P,5,FALSE) -> TGLS | C82: =VLOOKUP(A82,'JV and CTP清单'!C:P,13,FALSE) -> Hong Kong
A83: 名气家投资有限公司 | B83: =VLOOKUP(A83,'JV and CTP清单'!C:P,5,FALSE) -> MQJI | C83: =VLOOKUP(A83,'JV and CTP清单'!C:P,13,FALSE) -> Guangdong | D83: 名气家投资有限公司
A84: 名气通北京财务软件有限公司 | B84: =VLOOKUP(A84,'JV and CTP清单'!C:P,5,FALSE) -> TTBF | C84: =VLOOKUP(A84,'JV and CTP清单'!C:P,13,FALSE) -> Hong Kong
A85: 名气通北京信息服务有限公司 | B85: =VLOOKUP(A85,'JV and CTP清单'!C:P,5,FALSE) -> TTBI | C85: =VLOOKUP(A85,'JV and CTP清单'!C:P,13,FALSE) -> Hong Kong
A86: 名气通电讯（威海）有限公司 | B86: =VLOOKUP(A86,'JV and CTP清单'!C:P,5,FALSE) -> TTWH | C86: =VLOOKUP(A86,'JV and CTP清单'!C:P,13,FALSE) -> BVI
A87: 名气通电讯（中国）有限公司 | B87: =VLOOKUP(A87,'JV and CTP清单'!C:P,5,FALSE) -> TTCH | C87: =VLOOKUP(A87,'JV and CTP清单'!C:P,13,FALSE) -> BVI
A88: 名气通电讯固网有限公司 | B88: =VLOOKUP(A88,'JV and CTP清单'!C:P,5,FALSE) -> TFTN | C88: =VLOOKUP(A88,'JV and CTP清单'!C:P,13,FALSE) -> Hong Kong
A89: 名气通电讯有限公司 | B89: =VLOOKUP(A89,'JV and CTP清单'!C:P,5,FALSE) -> TTCLR | C89: =VLOOKUP(A89,'JV and CTP清单'!C:P,13,FALSE) -> Hong Kong
A90: 名气通丰县有限公司 | B90: =VLOOKUP(A90,'JV and CTP清单'!C:P,5,FALSE) -> TTFX | C90: =VLOOKUP(A90,'JV and CTP清单'!C:P,13,FALSE) -> Hong Kong
A91: 名气通哈尔滨有限公司 | B91: =VLOOKUP(A91,'JV and CTP清单'!C:P,5,FALSE) -> TTHB | C91: =VLOOKUP(A91,'JV and CTP清单'!C:P,13,FALSE) -> Hong Kong
A92: 名气通科技城（大连）有限公司 | B92: =VLOOKUP(A92,'JV and CTP清单'!C:P,5,FALSE) -> TTDC | C92: =VLOOKUP(A92,'JV and CTP清单'!C:P,13,FALSE) -> Hong Kong
A93: 名气通莱阳有限公司 | B93: =VLOOKUP(A93,'JV and CTP清单'!C:P,5,FALSE) -> TTLY | C93: =VLOOKUP(A93,'JV and CTP清单'!C:P,13,FALSE) -> Hong Kong
A94: 名气通沛县有限公司 | B94: =VLOOKUP(A94,'JV and CTP清单'!C:P,5,FALSE) -> TTPX | C94: =VLOOKUP(A94,'JV and CTP清单'!C:P,13,FALSE) -> Hong Kong
A95: 名气通深圳数据服务有限公司 | B95: =VLOOKUP(A95,'JV and CTP清单'!C:P,5,FALSE) -> TTSC | C95: =VLOOKUP(A95,'JV and CTP清单'!C:P,13,FALSE) -> Hong Kong
... A106: 秦皇岛易腾商贸有限公司 | B106: =VLOOKUP(A106,'JV and CTP清单'!C:P,5,FALSE) -> QHDTJV | C106: =VLOOKUP(A106,'JV and CTP清单'!C:P,13,FALSE) -> Hebei
A107: 青岛市莱西港能清洁能源有限公司 (Disable) | B107: =VLOOKUP(A107,'JV and CTP清单'!C:P,5,FALSE) -> SDLXCE | C107: =VLOOKUP(A107,'JV and CTP清单'!C:P,13,FALSE) -> Shandong | D107: 青岛市莱西港能清洁能源有限公司
A108: 饶平港华燃气有限公司 | B108: =VLOOKUP(A108,'JV and CTP清单'!C:P,5,FALSE) -> HXJV | C108: =VLOOKUP(A108,'JV and CTP清单'!C:P,13,FALSE) -> Guangdong
A109: 山东嘉祥易隆港务有限公司 | B109: =VLOOKUP(A109,'JV and CTP清单'!C:P,5,FALSE) -> JXHSJV | C109: =VLOOKUP(A109,'JV and CTP清单'!C:P,13,FALSE) -> Shandong
A110: 山西原平国新压缩天然气有限公司 | B110: =VLOOKUP(A110,'JV and CTP清单'!C:P,5,FALSE) -> YPJV | C110: =VLOOKUP(A110,'JV and CTP清单'!C:P,13,FALSE) -> Shanxi
A111: 上海名气通数据服务有限公司 | B111: =VLOOKUP(A111,'JV and CTP清单'!C:P,5,FALSE) -> TTSH | C111: =VLOOKUP(A111,'JV and CTP清单'!C:P,13,FALSE) -> Hong Kong
A112: 深圳北科兰光能源系统技术有限责任公司 | B112: =VLOOKUP(A112,'JV and CTP清单'!C:P,5,FALSE) -> BKLG | C112: =VLOOKUP(A112,'JV and CTP清单'!C:P,13,FALSE) -> Guangdong
A113: 深圳港华慧能科技有限公司（合并） | B113: =VLOOKUP(A113,'JV and CTP清单'!C:P,5,FALSE) -> GDSZGCE | C113: =VLOOKUP(A113,'JV and CTP清单'!C:P,13,FALSE) -> Guangdong | D113: 深圳港华慧能科技有限公司
A114: 深圳市創冷科技有限公司 | B114: =VLOOKUP(A114,'JV and CTP清单'!C:P,5,FALSE) -> 0 | C114: =VLOOKUP(A114,'JV and CTP清单'!C:P,13,FALSE) -> #N/A
A115: 深圳市互通联宽带网络有限公司 | B115: =VLOOKUP(A115,'JV and CTP清单'!C:P,5,FALSE) -> TTIEJV | C115: =VLOOKUP(A115,'JV and CTP清单'!C:P,13,FALSE) -> Guangdong
A116: 声耀投资有限公司 | B116: =VLOOKUP(A116,'JV and CTP清单'!C:P,5,FALSE) -> PCIL | C116: =VLOOKUP(A116,'JV and CTP清单'!C:P,13,FALSE) -> Hong Kong
A117: 盛港投资有限公司 | B117: =VLOOKUP(A117,'JV and CTP清单'!C:P,5,FALSE) -> SKIL | C117: =VLOOKUP(A117,'JV and CTP清单'!C:P,13,FALSE) -> Hong Kong
A118: 时代城市发展（常州）有限公司 | B118: =VLOOKUP(A118,'JV and CTP清单'!C:P,5,FALSE) -> EICCJV | C118: =VLOOKUP(A118,'JV and CTP清单'!C:P,13,FALSE) -> Jiangsu | D118: 时代城市发展（常州）有限公司
A119: 苏州工业园区苏相合作区市政公用发展有限公司 | B119: =VLOOKUP(A119,'JV and CTP清单'!C:P,5,FALSE) -> SIJV | C119: =VLOOKUP(A119,'JV and CTP清单'!C:P,13,FALSE) -> Jiangsu
A120: 睢宁县晶能光伏电力有限公司 | B120: =VLOOKUP(A120,'JV and CTP清单'!C:P,5,FALSE) -> JSSNJEL | C120: =VLOOKUP(A120,'JV and CTP清单'!C:P,13,FALSE) -> Jiangsu
A121: 唐山卓惠洗涤有限公司 | B121: =VLOOKUP(A121,'JV and CTP清单'!C:P,5,FALSE) -> CTECTS | C121: =VLOOKUP(A121,'JV and CTP清单'!C:P,13,FALSE) -> #N/A
A122: 天宏有限公司 | B122: =VLOOKUP(A122,'JV and CTP清单'!C:P,5,FALSE) -> HKJC | C122: =VLOOKUP(A122,'JV and CTP清单'!C:P,13,FALSE) -> BVI
A123: 天盛有限公司 | B123: =VLOOKUP(A123,'JV and CTP清单'!C:P,5,FALSE) -> SKYB | C123: =VLOOKUP(A123,'JV and CTP清单'!C:P,13,FALSE) -> BVI
A124: 威卓企业有限公司 | B124: =VLOOKUP(A124,'JV and CTP清单'!C:P,5,FALSE) -> EPEL | C124: =VLOOKUP(A124,'JV and CTP清单'!C:P,13,FALSE) -> BVI
A125: 伟诚倡投资有限公司 | B125: =VLOOKUP(A125,'JV and CTP清单'!C:P,5,FALSE) -> SMOO | C125: =VLOOKUP(A125,'JV and CTP清单'!C:P,13,FALSE) -> Hong Kong
A126: 乌拉特前旗新德宝商贸有限公司 | B126: =VLOOKUP(A126,'JV and CTP清单'!C:P,5,FALSE) -> UXDBJV | C126: =VLOOKUP(A126,'JV and CTP清单'!C:P,13,FALSE) -> Inner Mongoria
A127: 乌拉特中旗鑫冉天然气有限公司 | B127: =VLOOKUP(A127,'JV and CTP清单'!C:P,5,FALSE) -> UMBXJV | C127: =VLOOKUP(A127,'JV and CTP清单'!C:P,13,FALSE) -> Inner Mongoria
A128: 乌兰察布市丰华商贸有限公司 | B128: =VLOOKUP(A128,'JV and CTP清单'!C:P,5,FALSE) -> ULCBJV | C128: =VLOOKUP(A128,'JV and CTP清单'!C:P,13,FALSE) -> Inner Mongoria
A129: 香港煤气有限公司 | B129: =VLOOKUP(A129,'JV and CTP清单'!C:P,5,FALSE) -> HGAS | C129: =VLOOKUP(A129,'JV and CTP清单'!C:P,13,FALSE) -> Hong Kong
A130: 香港氫能聯盟有限公司 | B130: =VLOOKUP(A130,'JV and CTP清单'!C:P,5,FALSE) -> 0 | C130: =VLOOKUP(A130,'JV and CTP清单'!C:P,13,FALSE) -> Hong Kong
... A139: 徐州普未光合能源科技有限公司 | B139: =VLOOKUP(A139,'JV and CTP清单'!C:P,5,FALSE) -> JSXYE | C139: =VLOOKUP(A139,'JV and CTP清单'!C:P,13,FALSE) -> Jiangsu
A140: 宣城坤能新能源科技有限公司 | B140: =VLOOKUP(A140,'JV and CTP清单'!C:P,5,FALSE) -> AHXCKNE | C140: =VLOOKUP(A140,'JV and CTP清单'!C:P,13,FALSE) -> Anhui | D140: 宣城坤能新能源有限公司
A141: 烟台港能投光伏有限公司 | B141: =VLOOKUP(A141,'JV and CTP清单'!C:P,5,FALSE) -> PVYTJV | C141: =VLOOKUP(A141,'JV and CTP清单'!C:P,13,FALSE) -> Shandong
A142: 烟台市港能清洁能源有限公司（合并） | B142: =VLOOKUP(A142,'JV and CTP清单'!C:P,5,FALSE) -> 0 | C142: =VLOOKUP(A142,'JV and CTP清单'!C:P,13,FALSE) -> Shandong | D142: 烟台市港能清洁能源有限公司
A143: 衍华水务（中国）有限公司 (HK) | B143: =VLOOKUP(A143,'JV and CTP清单'!C:P,5,FALSE) -> HKCX | C143: =VLOOKUP(A143,'JV and CTP清单'!C:P,13,FALSE) -> Hong Kong
A144: 宜安（内蒙古）控股有限公司 | B144: =VLOOKUP(A144,'JV and CTP清单'!C:P,5,FALSE) -> YAIMJV | C144: =VLOOKUP(A144,'JV and CTP清单'!C:P,13,FALSE) -> Inner Mongoria
A145: 应通名气网络服务（深圳）有限公司 | B145: =VLOOKUP(A145,'JV and CTP清单'!C:P,5,FALSE) -> TNYTJV | C145: =VLOOKUP(A145,'JV and CTP清单'!C:P,13,FALSE) -> Guangdong
A146: 长春燃气股份有限公司 | B146: =VLOOKUP(A146,'JV and CTP清单'!C:P,5,FALSE) -> N/A | C146: =VLOOKUP(A146,'JV and CTP清单'!C:P,13,FALSE) -> Jilin
...
